Workbook

Sheet Cover
B2: NETFLIX, INC.
B3: NASDAQ: NFLX | Independent Equity-Research-Style Financial Model
B5: Three-Statement Operating Model • Scenario Analysis (Worst / Neutral / Best) • DCF Valuation
B8: A bottom-up, three-statement model built from Netflix's FY2023-FY2025 actuals, with a live scenario engine (Worst / Neutral / Best) driving revenue, margins, working capital, and a DCF valuation. Built as a portfolio project to demonstrate FP&A-style financial modeling: linked statements, sourced assumptions, and a documented audit trail -- not just a static forecast.
B9: Data source: FY2025 Form 10-K (SEC accession 0001065280-26-000034, filed 2026-01-23), covering FY2023-FY2025 actuals. Prepared July 2026.
B16: How to use this model
B17: 1. Set the scenario on the 'Model Control' tab (cell B3: pick Worst / Neutral / Best from the dropdown). This is the single master switch -- every tab updates from it.
B18: 2. 'Assumptions' holds every driver with its rationale, sourced to the 10-K MD&A where Netflix discloses one, and flagged where a figure is an analyst estimate. One tab, one format.
B19: 3. 'Proj Drivers' resolves the selected scenario into single driver values; 'Proj Schedules' builds the supporting rollforwards (revenue by region, content assets, PP&E, debt, working capital, equity).
B20: 4. 'Projected PnL / BS / CFS' are the fully linked three-statement output. 'Checks' confirms the balance sheet balances and cash ties out under every scenario.
B21: 5. 'WACC' and 'DCF' derive an intrinsic value per share and compare it to the market price.
B23: A note on methodology: why this model is revenue-driven, not subscriber-driven
... B51: 'Chart Data' computes Worst/Neutral/Best in parallel (independent of the Model Control switch) so all three scenarios can be charted at once. 'Charts' holds 7 native, editable Excel charts: Revenue, Cost of Revenue, Operating Expenses, Operating Income, Net Profit, and Operating Margin % (each with 3 scenario lines), plus a regional revenue mix chart for the Neutral case.

Sheet Model Control
A1: Model Control — Scenario Selector & Projection Assumptions
A2: NOTE: This is the single master scenario switch for the whole model (drives Assumptions, Proj Drivers, Chart Data, and every projected statement).
A3: Select Scenario (dropdown) -> | B3: Neutral | C3: =MATCH($B$3,{"Worst","Neutral","Best"},0) -> 2 | D3: (numeric index -- every CHOOSE() formula in the model reads this cell; do not edit directly, use the dropdown in B3)
A4: Active scenario | C4: =CHOOSE($C$3,"Worst Case","Neutral Case","Best Case") -> Neutral Case
A6: Single-point operating drivers (not scenario-varied; not year-by-year) -- see Assumptions tab for all scenario-driven % drivers
A10: Capex as % of revenue | C10: 0.015
A11: Depreciation as % of opening PP&E | C11: ='CFS Input'!D9/'Balance Sheet Input'!C11 -> 0.20918447 | D11: <- corrected: was hardcoded at 7.0%, a 3x understatement vs the actual 2025A ratio; now a live formula.
A12: Content amortization as % of opening content | C12: 0.5
A13: Current content liabilities as % of revenue | C13: 0.09
A14: Non-current content liabilities as % of revenue | C14: 0.035
A15: Other non-current assets as % of revenue | C15: 0.1725
A16: Other non-current liabilities as % of revenue | C16: 0.0655
A17: Stock-based compensation as % of revenue | C17: 0.0082
A18: Stock issuance proceeds as % of revenue | C18: 0.0148
A19: Debt weighted-average interest rate | C19: =Debt!D55 -> 0.0476 | D19: <- corrected: was a hardcoded flat 5.0% guess; now linked to the Debt tab's actual note-by-note weighted-average rate (4.76%).
A20: Short-term investments (held flat) | C20: 28678
A22: Share repurchases (capital-return policy) by year — KEY INPUT | C22: 2026E | D22: 2027E | E22: 2028E | F22: 2029E | G22: 2030E
A23: Buybacks | C23: 9127167 | D23: 9127167 | E23: 9127167 | F23: 9127167 | G23: 9127167

Sheet Assumptions
A1: Netflix, Inc. — Assumptions (single source of truth for all scenario drivers)
A2: Percent drivers stored as fractions; $ drivers in USD thousands. Source: FY2025 Form 10-K MD&A unless flagged as analyst estimate. The model reads only the "Selected" row of each block, which follows Model Control!B3.
A4: UCAN Revenue Growth %
A5: UCAN grew 15.0%-16.7% in 2024-2025, but that was inflated by two one-time catalysts: the 2023 paid-sharing crackdown converting freeloaders to payers, and the ad-tier ramping from launch. UCAN is Netflix's most penetrated market, so Neutral (5%) assumes that tailwind fades and growth reverts to a price-led, low-single-to-mid-single-digit pace. Worst (3%) reflects price-increase pushback/churn or a weaker ad-tier ramp; Best (7%) assumes stronger pricing power and live-sports/events engagement than the base case.
A6: Scenario | C6: 2025A | D6: 2026E | E6: 2027E | F6: 2028E | G6: 2029E | H6: 2030E
A7: Worst | C7: 0.03 | D7: 0.03 | E7: 0.03 | F7: 0.03 | G7: 0.03 | H7: 0.03
A8: Neutral | C8: 0.05 | D8: 0.05 | E8: 0.05 | F8: 0.05 | G8: 0.05 | H8: 0.05
A9: Best | C9: 0.07 | D9: 0.07 | E9: 0.07 | F9: 0.07 | G9: 0.07 | H9: 0.07
A10: Selected (drives model) | C10: =CHOOSE(MATCH('Model Control'!$B$3,{"Worst","Neutral","Best"},0),C7,C8,C9) -> 0.05 | D10: =CHOOSE(MATCH('Model Control'!$B$3,{"Worst","Neutral","Best"},0),D7,D8,D9) -> 0.05 | E10: =CHOOSE(MATCH('Model Control'!$B$3,{"Worst","Neutral","Best"},0),E7,E8,E9) -> 0.05 | F10: =CHOOSE(MATCH('Model Control'!$B$3,{"Worst","Neutral","Best"},0),F7,F8,F9) -> 0.05 | G10: =CHOOSE(MATCH('Model Control'!$B$3,{"Worst","Neutral","Best"},0),G7,G8,G9) -> 0.05 | H10: =CHOOSE(MATCH('Model Control'!$B$3,{"Worst","Neutral","Best"},0),H7,H8,H9) -> 0.05
A12: EMEA Revenue Growth %
A13: EMEA grew 17.2%-17.3% in 2024-2025, aided by the same paid-sharing/ad-tier tailwinds as UCAN, but off a lower penetration base with more runway. Neutral (9%) assumes roughly half the trailing rate persists as the denominator grows and the one-time boost fades. Worst (6%) reflects European macro softness or FX drag on reported USD revenue; Best (12%) assumes penetration gains continue closer to the trailing pace.
A14: Scenario | C14: 2025A | D14: 2026E | E14: 2027E | F14: 2028E | G14: 2029E | H14: 2030E
A15: Worst | C15: 0.06 | D15: 0.06 | E15: 0.06 | F15: 0.06 | G15: 0.06 | H15: 0.06
A16: Neutral | C16: 0.09 | D16: 0.09 | E16: 0.09 | F16: 0.09 | G16: 0.09 | H16: 0.09
A17: Best | C17: 0.12 | D17: 0.12 | E17: 0.12 | F17: 0.12 | G17: 0.12 | H17: 0.12
A18: Selected (drives model) | C18: =CHOOSE(MATCH('Model Control'!$B$3,{"Worst","Neutral","Best"},0),C15,C16,C17) -> 0.09 | D18: =CHOOSE(MATCH('Model Control'!$B$3,{"Worst","Neutral","Best"},0),D15,D16,D17) -> 0.09 | E18: =CHOOSE(MATCH('Model Control'!$B$3,{"Worst","Neutral","Best"},0),E15,E16,E17) -> 0.09 | F18: =CHOOSE(MATCH('Model Control'!$B$3,{"Worst","Neutral","Best"},0),F15,F16,F17) -> 0.09 | G18: =CHOOSE(MATCH('Model Control'!$B$3,{"Worst","Neutral","Best"},0),G15,G16,G17) -> 0.09 | H18: =CHOOSE(MATCH('Model Control'!$B$3,{"Worst","Neutral","Best"},0),H15,H16,H17) -> 0.09
A20: LATAM Revenue Growth %
A21: LATAM grew 8.8%-10.7% in 2024-2025, the slowest major region historically due to price sensitivity and FX volatility (Brazil, Argentina). Neutral (8%) is close to trailing, since LATAM didn't see as large a one-time step-up. Worst (5%) reflects currency devaluation and local-competitor pricing pressure; Best (11%) assumes continued household growth without a major FX shock.
A22: Scenario | C22: 2025A | D22: 2026E | E22: 2027E | F22: 2028E | G22: 2029E | H22: 2030E
A23: Worst | C23: 0.05 | D23: 0.05 | E23: 0.05 | F23: 0.05 | G23: 0.05 | H23: 0.05
A24: Neutral | C24: 0.08 | D24: 0.08 | E24: 0.08 | F24: 0.08 | G24: 0.08 | H24: 0.08
A25: Best | C25: 0.11 | D25: 0.11 | E25: 0.11 | F25: 0.11 | G25: 0.11 | H25: 0.11
A26: Selected (drives model) | C26: =CHOOSE(MATCH('Model Control'!$B$3,{"Worst","Neutral","Best"},0),C23,C24,C25) -> 0.08 | D26: =CHOOSE(MATCH('Model Control'!$B$3,{"Worst","Neutral","Best"},0),D23,D24,D25) -> 0.08 | E26: =CHOOSE(MATCH('Model Control'!$B$3,{"Worst","Neutral","Best"},0),E23,E24,E25) -> 0.08 | F26: =CHOOSE(MATCH('Model Control'!$B$3,{"Worst","Neutral","Best"},0),F23,F24,F25) -> 0.08 | G26: =CHOOSE(MATCH('Model Control'!$B$3,{"Worst","Neutral","Best"},0),G23,G24,G25) -> 0.08 | H26: =CHOOSE(MATCH('Model Control'!$B$3,{"Worst","Neutral","Best"},0),H23,H24,H25) -> 0.08
A28: APAC Revenue Growth %
A29: APAC grew 17.3%-21.3% in 2024-2025, the fastest-accelerating region, off the lowest penetration base (India, Japan, Korea are still under-penetrated). Neutral (12%) assumes deceleration from the 2025 peak as comps normalize, but keeps APAC as the highest-growth region since whitespace is real, not just a one-time conversion effect. Worst (8%) reflects slower India monetization or local-content underperformance; Best (16%) assumes the 2025 pace largely holds.
A30: Scenario | C30: 2025A | D30: 2026E | E30: 2027E | F30: 2028E | G30: 2029E | H30: 2030E
A31: Worst | C31: 0.08 | D31: 0.08 | E31: 0.08 | F31: 0.08 | G31: 0.08 | H31: 0.08
A32: Neutral | C32: 0.12 | D32: 0.12 | E32: 0.12 | F32: 0.12 | G32: 0.12 | H32: 0.12
A33: Best | C33: 0.16 | D33: 0.16 | E33: 0.16 | F33: 0.16 | G33: 0.16 | H33: 0.16
A34: Selected (drives model) | C34: =CHOOSE(MATCH('Model Control'!$B$3,{"Worst","Neutral","Best"},0),C31,C32,C33) -> 0.12 | D34: =CHOOSE(MATCH('Model Control'!$B$3,{"Worst","Neutral","Best"},0),D31,D32,D33) -> 0.12 | E34: =CHOOSE(MATCH('Model Control'!$B$3,{"Worst","Neutral","Best"},0),E31,E32,E33) -> 0.12 | F34: =CHOOSE(MATCH('Model Control'!$B$3,{"Worst","Neutral","Best"},0),F31,F32,F33) -> 0.12 | G34: =CHOOSE(MATCH('Model Control'!$B$3,{"Worst","Neutral","Best"},0),G31,G32,G33) -> 0.12 | H34: =CHOOSE(MATCH('Model Control'!$B$3,{"Worst","Neutral","Best"},0),H31,H32,H33) -> 0.12
A36: Content Spend (Additions) Growth %
A37: Content spend is not separately guided by Netflix, so this is modeled as a rate relative to revenue growth, not an independent estimate. Neutral (10%) tracks below Neutral revenue growth (7-9%), consistent with content spend growing but content cost intensity gradually declining as the library monetizes over more subscribers. Worst (15%) assumes content cost inflation (competitive bidding for sports/marquee titles) outpaces revenue; Best (7%) assumes tighter content ROI discipline.
A38: Scenario | C38: 2025A | D38: 2026E | E38: 2027E | F38: 2028E | G38: 2029E | H38: 2030E
A39: Worst | C39: 0.15 | D39: 0.15 | E39: 0.15 | F39: 0.15 | G39: 0.15 | H39: 0.15
A40: Neutral | C40: 0.1 | D40: 0.1 | E40: 0.1 | F40: 0.1 | G40: 0.1 | H40: 0.1
A41: Best | C41: 0.07 | D41: 0.07 | E41: 0.07 | F41: 0.07 | G41: 0.07 | H41: 0.07
A42: Selected (drives model) | C42: =CHOOSE(MATCH('Model Control'!$B$3,{"Worst","Neutral","Best"},0),C39,C40,C41) -> 0.1 | D42: =CHOOSE(MATCH('Model Control'!$B$3,{"Worst","Neutral","Best"},0),D39,D40,D41) -> 0.1 | E42: =CHOOSE(MATCH('Model Control'!$B$3,{"Worst","Neutral","Best"},0),E39,E40,E41) -> 0.1 | F42: =CHOOSE(MATCH('Model Control'!$B$3,{"Worst","Neutral","Best"},0),F39,F40,F41) -> 0.1 | G42: =CHOOSE(MATCH('Model Control'!$B$3,{"Worst","Neutral","Best"},0),G39,G40,G41) -> 0.1 | H42: =CHOOSE(MATCH('Model Control'!$B$3,{"Worst","Neutral","Best"},0),H39,H40,H41) -> 0.1
A44: Cost of Revenues (% of Revenue)
A45: Cost of revenue was 51.5% of revenue in 2025A (2025A cell is now a live formula, not hardcoded, so it can never drift from the historicals again). Netflix has publicly guided toward continued operating margin expansion as the platform scales. Neutral assumes ~25-30bps/year of leverage (51.5% to ~50.0% by 2030). Worst assumes leverage stalls and the ratio drifts up (~52.5% by 2030) from content-cost inflation or competitive spend; Best assumes leverage accelerates (~48.3%) if ad-tier and live content scale efficiently against largely fixed platform costs.
A46: Scenario | C46: 2025A | D46: 2026E | E46: 2027E | F46: 2028E | G46: 2029E | H46: 2030E
A47: Worst | C47: ='P&L Input'!E4/'P&L Input'!E3 -> 0.51513424 | D47: 0.517134 | E47: 0.519134 | F47: 0.520134 | G47: 0.522134 | H47: 0.525134
A48: Neutral | C48: ='P&L Input'!E4/'P&L Input'!E3 -> 0.51513424 | D48: 0.512134 | E48: 0.509134 | F48: 0.506134 | G48: 0.503134 | H48: 0.500134
A49: Best | C49: ='P&L Input'!E4/'P&L Input'!E3 -> 0.51513424 | D49: 0.508134 | E49: 0.501134 | F49: 0.494134 | G49: 0.488134 | H49: 0.483134
A50: Selected (drives model) | C50: =CHOOSE(MATCH('Model Control'!$B$3,{"Worst","Neutral","Best"},0),C47,C48,C49) -> 0.51513424 | D50: =CHOOSE(MATCH('Model Control'!$B$3,{"Worst","Neutral","Best"},0),D47,D48,D49) -> 0.512134 | E50: =CHOOSE(MATCH('Model Control'!$B$3,{"Worst","Neutral","Best"},0),E47,E48,E49) -> 0.509134 | F50: =CHOOSE(MATCH('Model Control'!$B$3,{"Worst","Neutral","Best"},0),F47,F48,F49) -> 0.506134 | G50: =CHOOSE(MATCH('Model Control'!$B$3,{"Worst","Neutral","Best"},0),G47,G48,G49) -> 0.503134 | H50: =CHOOSE(MATCH('Model Control'!$B$3,{"Worst","Neutral","Best"},0),H47,H48,H49) -> 0.500134
A52: Sales & Marketing (% of Revenue)
A53: S&M was 7.3% of revenue in 2025A (live formula). Neutral assumes modest leverage (7.3% to 6.8%) as brand awareness matures. Worst (7.3% to 8.3%) assumes continued heavy ad-sales investment without payoff; Best (7.3% to 6.0%) assumes the ad business reaches scale efficiency faster than the base case.
A54: Scenario | C54: 2025A | D54: 2026E | E54: 2027E | F54: 2028E | G54: 2029E | H54: 2030E
A55: Worst | C55: ='P&L Input'!E6/'P&L Input'!E3 -> 0.073065165 | D55: 0.076065 | E55: 0.078065 | F55: 0.080065 | G55: 0.082065 | H55: 0.083065
A56: Neutral | C56: ='P&L Input'!E6/'P&L Input'!E3 -> 0.073065165 | D56: 0.072065 | E56: 0.071065 | F56: 0.070065 | G56: 0.069065 | H56: 0.068065
A57: Best | C57: ='P&L Input'!E6/'P&L Input'!E3 -> 0.073065165 | D57: 0.070065 | E57: 0.067065 | F57: 0.064065 | G57: 0.062065 | H57: 0.060065
A58: Selected (drives model) | C58: =CHOOSE(MATCH('Model Control'!$B$3,{"Worst","Neutral","Best"},0),C55,C56,C57) -> 0.073065165 | D58: =CHOOSE(MATCH('Model Control'!$B$3,{"Worst","Neutral","Best"},0),D55,D56,D57) -> 0.072065 | E58: =CHOOSE(MATCH('Model Control'!$B$3,{"Worst","Neutral","Best"},0),E55,E56,E57) -> 0.071065 | F58: =CHOOSE(MATCH('Model Control'!$B$3,{"Worst","Neutral","Best"},0),F55,F56,F57) -> 0.070065 | G58: =CHOOSE(MATCH('Model Control'!$B$3,{"Worst","Neutral","Best"},0),G55,G56,G57) -> 0.069065 | H58: =CHOOSE(MATCH('Model Control'!$B$3,{"Worst","Neutral","Best"},0),H55,H56,H57) -> 0.068065
A60: Technology & Development (% of Revenue)
A61: Tech & Dev was 7.5% of revenue in 2025A (live formula). Neutral assumes slow leverage (7.5% to 7.1%). Worst (7.5% to 8.3%) assumes continued heavy ad-tech/gaming investment without leverage; Best (7.5% to 6.7%) assumes platform investment plateaus while revenue keeps growing.
A62: Scenario | C62: 2025A | D62: 2026E | E62: 2027E | F62: 2028E | G62: 2029E | H62: 2030E
A63: Worst | C63: ='P&L Input'!E7/'P&L Input'!E3 -> 0.075058923 | D63: 0.077059 | E63: 0.078059 | F63: 0.080059 | G63: 0.081059 | H63: 0.083059
A64: Neutral | C64: ='P&L Input'!E7/'P&L Input'!E3 -> 0.075058923 | D64: 0.075059 | E64: 0.074059 | F64: 0.073059 | G64: 0.072059 | H64: 0.071059
A65: Best | C65: ='P&L Input'!E7/'P&L Input'!E3 -> 0.075058923 | D65: 0.073059 | E65: 0.071059 | F65: 0.070059 | G65: 0.068059 | H65: 0.067059
A66: Selected (drives model) | C66: =CHOOSE(MATCH('Model Control'!$B$3,{"Worst","Neutral","Best"},0),C63,C64,C65) -> 0.075058923 | D66: =CHOOSE(MATCH('Model Control'!$B$3,{"Worst","Neutral","Best"},0),D63,D64,D65) -> 0.075059 | E66: =CHOOSE(MATCH('Model Control'!$B$3,{"Worst","Neutral","Best"},0),E63,E64,E65) -> 0.074059 | F66: =CHOOSE(MATCH('Model Control'!$B$3,{"Worst","Neutral","Best"},0),F63,F64,F65) -> 0.073059 | G66: =CHOOSE(MATCH('Model Control'!$B$3,{"Worst","Neutral","Best"},0),G63,G64,G65) -> 0.072059 | H66: =CHOOSE(MATCH('Model Control'!$B$3,{"Worst","Neutral","Best"},0),H63,H64,H65) -> 0.071059
A68: General & Administrative (% of Revenue)
A69: G&A was 4.2% of revenue in 2025A (live formula; 2025 elevated by WBD-transaction-related costs, treated as non-recurring). Neutral assumes leverage back toward historical norms (4.2% to 3.7%). Worst (4.2% to 5.0%) assumes continued elevated legal/M&A-related costs; Best (4.2% to 3.2%) assumes a clean reversion.
A70: Scenario | C70: 2025A | D70: 2026E | E70: 2027E | F70: 2028E | G70: 2029E | H70: 2030E
A71: Worst | C71: ='P&L Input'!E8/'P&L Input'!E3 -> 0.041794624 | D71: 0.043795 | E71: 0.044795 | F71: 0.046795 | G71: 0.047795 | H71: 0.049795
A72: Neutral | C72: ='P&L Input'!E8/'P&L Input'!E3 -> 0.041794624 | D72: 0.040795 | E72: 0.039795 | F72: 0.038795 | G72: 0.037795 | H72: 0.036795
A73: Best | C73: ='P&L Input'!E8/'P&L Input'!E3 -> 0.041794624 | D73: 0.038795 | E73: 0.036795 | F73: 0.034795 | G73: 0.033795 | H73: 0.031795
A74: Selected (drives model) | C74: =CHOOSE(MATCH('Model Control'!$B$3,{"Worst","Neutral","Best"},0),C71,C72,C73) -> 0.041794624 | D74: =CHOOSE(MATCH('Model Control'!$B$3,{"Worst","Neutral","Best"},0),D71,D72,D73) -> 0.040795 | E74: =CHOOSE(MATCH('Model Control'!$B$3,{"Worst","Neutral","Best"},0),E71,E72,E73) -> 0.039795 | F74: =CHOOSE(MATCH('Model Control'!$B$3,{"Worst","Neutral","Best"},0),F71,F72,F73) -> 0.038795 | G74: =CHOOSE(MATCH('Model Control'!$B$3,{"Worst","Neutral","Best"},0),G71,G72,G73) -> 0.037795 | H74: =CHOOSE(MATCH('Model Control'!$B$3,{"Worst","Neutral","Best"},0),H71,H72,H73) -> 0.036795
A76: Other Current Assets (% of Revenue)
A77: Other current assets were 8.8% of revenue in 2025A (live formula). A working-capital ratio, not a business driver -- Neutral holds it roughly flat (8.8% to 8.3%). Worst/Best reflect modest working-capital efficiency swings rather than a distinct business thesis.
A78: Scenario | C78: 2025A | D78: 2026E | E78: 2027E | F78: 2028E | G78: 2029E | H78: 2030E
A79: Worst | C79: ='Balance Sheet Input'!D8/'P&L Input'!E3 -> 0.08759553 | D79: 0.090596 | E79: 0.092596 | F79: 0.094596 | G79: 0.096596 | H79: 0.097596
A80: Neutral | C80: ='Balance Sheet Input'!D8/'P&L Input'!E3 -> 0.08759553 | D80: 0.087596 | E80: 0.086596 | F80: 0.085596 | G80: 0.084596 | H80: 0.083596
A81: Best | C81: ='Balance Sheet Input'!D8/'P&L Input'!E3 -> 0.08759553 | D81: 0.085596 | E81: 0.083596 | F81: 0.081596 | G81: 0.079596 | H81: 0.077596
A82: Selected (drives model) | C82: =CHOOSE(MATCH('Model Control'!$B$3,{"Worst","Neutral","Best"},0),C79,C80,C81) -> 0.08759553 | D82: =CHOOSE(MATCH('Model Control'!$B$3,{"Worst","Neutral","Best"},0),D79,D80,D81) -> 0.087596 | E82: =CHOOSE(MATCH('Model Control'!$B$3,{"Worst","Neutral","Best"},0),E79,E80,E81) -> 0.086596 | F82: =CHOOSE(MATCH('Model Control'!$B$3,{"Worst","Neutral","Best"},0),F79,F80,F81) -> 0.085596 | G82: =CHOOSE(MATCH('Model Control'!$B$3,{"Worst","Neutral","Best"},0),G79,G80,G81) -> 0.084596 | H82: =CHOOSE(MATCH('Model Control'!$B$3,{"Worst","Neutral","Best"},0),H79,H80,H81) -> 0.083596
A84: Accounts Payable -- Days Payable Outstanding (DPO)
A85: DPO was 14.1 days in 2025A. Neutral assumes stable payment-cycle management (14.1 to 14.5 days). Worst (14.1 to 12.8 days, i.e. paying suppliers faster / less favorable terms) reflects tighter supplier negotiating leverage in a downside scenario; Best (14.1 to 15.5 days) assumes Netflix extends payment terms as its scale/negotiating power grows -- a modest working-capital tailwind.
A86: Scenario | C86: 2025A | D86: 2026E | E86: 2027E | F86: 2028E | G86: 2029E | H86: 2030E
A87: Worst | C87: 14.1 | D87: 13.8 | E87: 13.5 | F87: 13.2 | G87: 13 | H87: 12.8
A88: Neutral | C88: 14.1 | D88: 14.2 | E88: 14.3 | F88: 14.4 | G88: 14.5 | H88: 14.5
A89: Best | C89: 14.1 | D89: 14.5 | E89: 14.8 | F89: 15 | G89: 15.2 | H89: 15.5
A90: Selected (drives model) | C90: =CHOOSE(MATCH('Model Control'!$B$3,{"Worst","Neutral","Best"},0),C87,C88,C89) -> 14.1 | D90: =CHOOSE(MATCH('Model Control'!$B$3,{"Worst","Neutral","Best"},0),D87,D88,D89) -> 14.2 | E90: =CHOOSE(MATCH('Model Control'!$B$3,{"Worst","Neutral","Best"},0),E87,E88,E89) -> 14.3 | F90: =CHOOSE(MATCH('Model Control'!$B$3,{"Worst","Neutral","Best"},0),F87,F88,F89) -> 14.4 | G90: =CHOOSE(MATCH('Model Control'!$B$3,{"Worst","Neutral","Best"},0),G87,G88,G89) -> 14.5 | H90: =CHOOSE(MATCH('Model Control'!$B$3,{"Worst","Neutral","Best"},0),H87,H88,H89) -> 14.5
A92: Accrued Expenses & Other Liabilities (% of Revenue)
A93: Accrued expenses were 7.1% of revenue in 2025A (live formula). Modeled with the same direction/magnitude as S&M for consistency: Neutral 7.1% to 6.7%, Worst 7.1% to 8.1%, Best 7.1% to 6.1%.
A94: Scenario | C94: 2025A | D94: 2026E | E94: 2027E | F94: 2028E | G94: 2029E | H94: 2030E
A95: Worst | C95: ='Balance Sheet Input'!D19/'P&L Input'!E3 -> 0.071284918 | D95: 0.074285 | E95: 0.076285 | F95: 0.078285 | G95: 0.080285 | H95: 0.081285
A96: Neutral | C96: ='Balance Sheet Input'!D19/'P&L Input'!E3 -> 0.071284918 | D96: 0.070285 | E96: 0.069285 | F96: 0.068285 | G96: 0.067285 | H96: 0.066285
A97: Best | C97: ='Balance Sheet Input'!D19/'P&L Input'!E3 -> 0.071284918 | D97: 0.068285 | E97: 0.066285 | F97: 0.064285 | G97: 0.062285 | H97: 0.061285
A98: Selected (drives model) | C98: =CHOOSE(MATCH('Model Control'!$B$3,{"Worst","Neutral","Best"},0),C95,C96,C97) -> 0.071284918 | D98: =CHOOSE(MATCH('Model Control'!$B$3,{"Worst","Neutral","Best"},0),D95,D96,D97) -> 0.070285 | E98: =CHOOSE(MATCH('Model Control'!$B$3,{"Worst","Neutral","Best"},0),E95,E96,E97) -> 0.069285 | F98: =CHOOSE(MATCH('Model Control'!$B$3,{"Worst","Neutral","Best"},0),F95,F96,F97) -> 0.068285 | G98: =CHOOSE(MATCH('Model Control'!$B$3,{"Worst","Neutral","Best"},0),G95,G96,G97) -> 0.067285 | H98: =CHOOSE(MATCH('Model Control'!$B$3,{"Worst","Neutral","Best"},0),H95,H96,H97) -> 0.066285
A100: Deferred Revenue (% of Revenue)
A101: Deferred revenue was 3.9% of revenue in 2025A (live formula) -- structurally one of the most stable ratios in the model given monthly-in-advance subscription billing. Neutral holds it essentially flat (3.9% to 3.8%).
A102: Scenario | C102: 2025A | D102: 2026E | E102: 2027E | F102: 2028E | G102: 2029E | H102: 2030E
A103: Worst | C103: ='Balance Sheet Input'!D20/'P&L Input'!E3 -> 0.039300812 | D103: 0.041301 | E103: 0.042301 | F103: 0.044301 | G103: 0.045301 | H103: 0.047301
A104: Neutral | C104: ='Balance Sheet Input'!D20/'P&L Input'!E3 -> 0.039300812 | D104: 0.039301 | E104: 0.039301 | F104: 0.038301 | G104: 0.038301 | H104: 0.037301
A105: Best | C105: ='Balance Sheet Input'!D20/'P&L Input'!E3 -> 0.039300812 | D105: 0.038301 | E105: 0.037301 | F105: 0.036301 | G105: 0.035301 | H105: 0.034301
A106: Selected (drives model) | C106: =CHOOSE(MATCH('Model Control'!$B$3,{"Worst","Neutral","Best"},0),C103,C104,C105) -> 0.039300812 | D106: =CHOOSE(MATCH('Model Control'!$B$3,{"Worst","Neutral","Best"},0),D103,D104,D105) -> 0.039301 | E106: =CHOOSE(MATCH('Model Control'!$B$3,{"Worst","Neutral","Best"},0),E103,E104,E105) -> 0.039301 | F106: =CHOOSE(MATCH('Model Control'!$B$3,{"Worst","Neutral","Best"},0),F103,F104,F105) -> 0.038301 | G106: =CHOOSE(MATCH('Model Control'!$B$3,{"Worst","Neutral","Best"},0),G103,G104,G105) -> 0.038301 | H106: =CHOOSE(MATCH('Model Control'!$B$3,{"Worst","Neutral","Best"},0),H103,H104,H105) -> 0.037301
A108: Interest & Other Income (Expense), $000s
A109: This line is FX-remeasurement and investment-income driven, which Netflix does not forecast and which is not systematically related to the operating scenario -- it is the least defensible line in the model on a bottom-up basis. Rather than build a detailed FX forecast, Worst/Neutral/Best are set directionally (unfavorable/neutral/favorable) around the 2025A actual of $172.5mm, and held small relative to EBT (under 2% of operating income in every year) so it does not meaningfully drive the scenario spread.
A110: Scenario | C110: 2025A | D110: 2026E | E110: 2027E | F110: 2028E | G110: 2029E | H110: 2030E
A111: Worst | C111: 172459 | D111: -75000 | E111: -50000 | F111: -25000 | G111: 0 | H111: 25000
A112: Neutral | C112: 172459 | D112: 50000 | E112: 75000 | F112: 100000 | G112: 100000 | H112: 125000
A113: Best | C113: 172459 | D113: 150000 | E113: 175000 | F113: 200000 | G113: 225000 | H113: 250000
A114: Selected (drives model) | C114: =CHOOSE(MATCH('Model Control'!$B$3,{"Worst","Neutral","Best"},0),C111,C112,C113) -> 172459 | D114: =CHOOSE(MATCH('Model Control'!$B$3,{"Worst","Neutral","Best"},0),D111,D112,D113) -> 50000 | E114: =CHOOSE(MATCH('Model Control'!$B$3,{"Worst","Neutral","Best"},0),E111,E112,E113) -> 75000 | F114: =CHOOSE(MATCH('Model Control'!$B$3,{"Worst","Neutral","Best"},0),F111,F112,F113) -> 100000 | G114: =CHOOSE(MATCH('Model Control'!$B$3,{"Worst","Neutral","Best"},0),G111,G112,G113) -> 100000 | H114: =CHOOSE(MATCH('Model Control'!$B$3,{"Worst","Neutral","Best"},0),H111,H112,H113) -> 125000
...

Sheet P&L Input
A1: P&L Statement | E1: (in thousands, except per share data)
C2: 2023 | D2: 2024 | E2: 2025
A3: Revenues | C3: 33723297 | D3: 39000966 | E3: 45183036
A4: Cost of revenues | C4: 19715368 | D4: 21038464 | E4: 23275329
C5: =C3-C4 -> 14007929 | D5: =D3-D4 -> 17962502 | E5: =E3-E4 -> 21907707
A6: Sales and marketing | C6: 2657883 | D6: 2917554 | E6: 3301306
A7: Technology and development | C7: 2675758 | D7: 2925295 | E7: 3391390
A8: General and administrative | C8: 1720285 | D8: 1702039 | E8: 1888408
A9: Operating income | C9: =C5-C6-C7-C8 -> 6954003 | D9: =D5-D6-D7-D8 -> 10417614 | E9: =E5-E6-E7-E8 -> 13326603
A10: Other income (expense):
A11: Interest expense | C11: -699826 | D11: -718733 | E11: -776510
A12: Interest and other income (expense) | C12: -48772 | D12: 266776 | E12: 172459
A13: Income before income taxes | C13: =C9+C11+C12 -> 6205405 | D13: =D9+D11+D12 -> 9965657 | E13: =E9+E11+E12 -> 12722552
A14: Provision for income taxes | C14: -797415 | D14: -1254026 | E14: -1741351
A15: Net income | C15: =SUM(C13:C14) -> 5407990 | D15: =D13+D14 -> 8711631 | E15: =E13+E14 -> 10981201
A17: Earnings per share:
A18: Basic | C18: 1.22 | D18: 2.03 | E18: 2.58
A19: Diluted | C19: 1.2 | D19: 1.98 | E19: 2.53
A20: Weighted-average shares of common stock outstanding:
A21: Basic | C21: 4,415,712 | D21: 4,295,191 | E21: 4,249,512
A22: Diluted | C22: 4,494,966 | D22: 4,392,608 | E22: 4,343,863
A25: Net income | C25: =C15 -> 5407990 | D25: =D15 -> 8711631 | E25: =E15 -> 10981201
A26: Other comprehensive income (loss):
A27: Foreign currency translation adjustments, net of income tax benefit (expense) of $33 million, $(7) million, and $0, respectively | C27: 113384 | D27: -247949 | E27: 72011
A28: Net change in unrealized gains (losses) on available-for-sale securities, net of income tax benefit (expense) of $1 million, $(1) million, and $0, respectively | D28: 2511 | E28: -2511
A29: Cash flow hedges:
A30: Net unrealized gains (losses) | C30: -120023 | D30: 921227 | E30: -1071168
A31: Reclassification of net (gains) losses included in net income | D31: -96795 | E31: 68962
A32: Net change, net of income tax benefit (expense) of $301 million, $(246) million, and $36 million, respectively | C32: =SUM(C30:C31) -> -120023 | D32: =SUM(D30:D31) -> 824432 | E32: =SUM(E30:E31) -> -1002206
A33: Fair value hedges:
A34: Net change in unrealized gains (losses) excluded from the assessment of effectiveness, net of income tax benefit (expense) of $3 million, $(2) million, and $0, respectively | D34: 7113 | E34: -9838
A35: Total other comprehensive income (loss) | C35: =C27+C28+C32+C34 -> -6639 | D35: =D27+D28+D32+D34 -> 586107 | E35: =E27+E28+E32+E34 -> -942544
A36: Comprehensive income | C36: =C25+C35 -> 5401351 | D36: =D25+D35 -> 9297738 | E36: =E25+E35 -> 10038657

Sheet Balance Sheet Input
A1: Balance Sheet | E1: in thousands, except share and per share data
B3: 2023 | C3: 2024 | D3: 2025
A4: Assets
A5: Current assets:
A6: Cash and cash equivalents | B6: 7116913 | C6: 7804733 | D6: 9033681 | F6: Cashflow
A7: Short-term investments | B7: 20973 | C7: 1779006 | D7: 28678
A8: Other current assets | B8: 2780247 | C8: 3516640 | D8: 3957832 | F8: Other Items
A9: Total current assets | B9: =SUM(B6:B8) -> 9918133 | C9: =SUM(C6:C8) -> 13100379 | D9: =SUM(D6:D8) -> 13020191
A10: Content assets, net | B10: 31658056 | C10: 32452462 | D10: 32778392 | F10: Schedules
A11: Property and equipment, net | B11: 1491444 | C11: 1593756 | D11: 2004350 | F11: Schedules
A12: Other non-current assets | B12: 5664359 | C12: 6483777 | D12: 7794060
A13: Total assets | B13: =SUM(B9:B12) -> 48731992 | C13: =SUM(C9:C12) -> 53630374 | D13: =SUM(D9:D12) -> 55596993
A15: Liabilities and Stockholders' Equity
A16: Current liabilities:
A17: Current content liabilities | B17: 4466470 | C17: 4393681 | D17: 4084854
A18: Accounts payable | B18: 747412 | C18: 899909 | D18: 900612 | F18: Other Items
A19: Accrued expenses and other liabilities | B19: 1803960 | C19: 2156544 | D19: 3220869
A20: Deferred revenue | B20: 1442969 | C20: 1520813 | D20: 1775730
A21: Short-term debt | B21: 399844 | C21: 1784453 | D21: 998865
A22: Total current liabilities | B22: =SUM(B17:B21) -> 8860655 | C22: =SUM(C17:C21) -> 10755400 | D22: =SUM(D17:D21) -> 10980930
A23: Non-current content liabilities | B23: 2578173 | C23: 1780806 | D23: 1579476
A24: Long-term debt | B24: 14143417 | C24: 13798351 | D24: 13463971
A25: Other non-current liabilities | B25: 2561434 | C25: 2552250 | D25: 2957128
A26: Total liabilities | B26: =SUM(B22:B25) -> 28143679 | C26: =SUM(C22:C25) -> 28886807 | D26: =SUM(D22:D25) -> 28981505
A27: Stockholders' equity:
A28: Common stock | B28: 5145172 | C28: 6252126 | D28: 7286410
A29: Treasury stock | B29: -6922200 | C29: -13171638 | D29: -22372658
A30: Accumulated other comprehensive income (loss) | B30: -223945 | C30: 362162 | D30: -580382
A31: Retained earnings | B31: 22589286 | C31: 31300917 | D31: 42282118
A32: Total stockholders' equity | B32: =SUM(B28:B31) -> 20588313 | C32: =SUM(C28:C31) -> 24743567 | D32: =SUM(D28:D31) -> 26615488
A33: Total liabilities and stockholders' equity | B33: =B26+B32 -> 48731992 | C33: =C26+C32 -> 53630374 | D33: =D26+D32 -> 55596993

Sheet CFS Input
A1: Cash Flow Statement (USD in thousands) | B1: 2023 | C1: 2024 | D1: 2025
A3: Cash flows from operating activities
A4: Net income | B4: 5407990 | C4: 8711631 | D4: 10981201
A5: Adjustments to reconcile net income to net cash provided by operating activities
A6: Additions to content assets | B6: -12554703 | C6: -16223617 | D6: -17096617
A7: Change in content liabilities | B7: -585602 | C7: -779135 | D7: -610838
A8: Amortization of content assets | B8: 14197437 | C8: 15301517 | D8: 16422166
A9: Depreciation and amortization of property, equipment and intangibles | B9: 356947 | C9: 328914 | D9: 333389
A10: Stock-based compensation expense | B10: 339368 | C10: 272588 | D10: 368449
A11: Foreign currency remeasurement loss (gain) on debt | B11: 176296 | C11: -121539 | D11: 72348
A12: Other non-cash items | B12: 512075 | C12: 494778 | D12: 577451
A13: Deferred income taxes | B13: -459359 | C13: -590698 | D13: -442056
A14: Changes in operating assets and liabilities
A15: Other current assets | B15: -181003 | C15: 22180 | D15: -790661
A16: Accounts payable | B16: 93502 | C16: 121353 | D16: -8039
A17: Accrued expenses and other liabilities | B17: 103565 | C17: 191899 | D17: 881218
A18: Deferred revenue | B18: 178708 | C18: 77844 | D18: 254917
A19: Other non-current assets and liabilities | B19: -310920 | C19: -446351 | D19: -793655
A20: Net cash provided by operating activities | B20: =SUM(B4:B19) -> 7274301 | C20: =SUM(C4:C19) -> 7361364 | D20: =SUM(D4:D19) -> 10149273
A22: Cash flows from investing activities
A23: Purchases of property and equipment | B23: -348552 | C23: -439538 | D23: -688220
A24: Acquisitions | B24: 0 | C24: 0 | D24: -17194
A25: Purchase of Investments | B25: -504862 | C25: -1742246 | D25: -169965
A26: Proceeds from maturities and sales of invesments | B26: 1395165 | C26: 0 | D26: 1917067
A27: Net cash provided by (used in) used in investing activities | B27: =SUM(B23:B26) -> 541751 | C27: =SUM(C23:C26) -> -2181784 | D27: =SUM(D23:D26) -> 1041688
A29: Cash flows from financing activities
A30: Proceeds from issuance of debt | B30: 0 | C30: 1794460 | D30: 0
A31: Repayment of debt | B31: 0 | C31: -400000 | D31: -1833450
A32: Proceeds from issuance of common stock | B32: 169990 | C32: 832887 | D32: 666965
A33: Repurchases of common stock | B33: -6045347 | C33: -6263746 | D33: -9127167
A34: Taxes paid related to net share settlement of equity awards | B34: 0 | C34: -8285 | D34: -46165
A35: Other financing activities | B35: -75446 | C35: -29743 | D35: -5806
A36: Net cash provided by (used in) financing activities | B36: =SUM(B30:B35) -> -5950803 | C36: =SUM(C30:C35) -> -4074427 | D36: =SUM(D30:D35) -> -10345623
A38: Effect of exchange rate changes on cash, cash equivalents and restricted cash | B38: 82684 | C38: -416331 | D38: 386519
A39: Net increase (decrease) in cash, cash equivalents and restricted cash | B39: =B20+B27+B36+B38 -> 1947933 | C39: =C20+C27+C36+C38 -> 688822 | D39: =D20+D27+D36+D38 -> 1231857
A41: Cash, cash equivalents and restricted cash at beginning of year | B41: 5170582 | C41: 7118515 | D41: 7807337
A42: Cash, cash equivalents and restricted cash at end of year | B42: =B39+B41 -> 7118515 | C42: =C39+C41 -> 7807337 | D42: =D39+D41 -> 9039194
A44: Supplemental disclosure
A45: Interest paid | B45: 684504 | C45: 674502 | D45: 718611

Sheet Revenue Modelling
A1: Revenue Sources
A3: Streaming revenues | B3: 2023 | C3: 2024 | D3: 2025
A4: United States and Canada (UCAN) | B4: 14873783 | C4: 17359369 | D4: 19957152
A5: Growth percentage | C5: =(C4-B4)/B4 -> 0.16711189 | D5: =(D4-C4)/C4 -> 0.14964732
A6: Europe, Middle East, and Africa (EMEA) | B6: 10556487 | C6: 12387035 | D6: 14514646
A7: Growth percentage | C7: =(C6-B6)/B6 -> 0.17340504 | D7: =(D6-C6)/C6 -> 0.17176112
A8: Latin America (LATAM) | B8: 4446461 | C8: 4839816 | D8: 5357521
A9: Growth percentage | C9: =(C8-B8)/B8 -> 0.088464736 | D9: =(D8-C8)/C8 -> 0.10696791
A10: Asia-Pacific (APAC) | B10: 3763727 | C10: 4414746 | D10: 5353717
A11: Growth percentage | C11: =(C10-B10)/B10 -> 0.1729719 | D11: =(D10-C10)/C10 -> 0.2126897
A12: Total Streaming Revenues | B12: 33640458 | C12: 39000966 | D12: 45183036
A13: Total growth percentage | C13: =(C12-B12)/B12 -> 0.15934706 | D13: =(D12-C12)/C12 -> 0.15851069
A15: DVD | B15: 82839
A17: Total Revenue | B17: 33723297 | C17: 39000966 | D17: 45183036
A19: Additional Points
A21: 1. Netflix discontinued DVD-by-mail service in the year ended December 31, 2023. The discontinuance of our DVD business had an immaterial impact on operations and financial results
A23: 2. During the year ended December 31, 2025, we discontinued the reporting of membership numbers, including average paying memberships and average monthly revenue per paying membership, focusing instead on revenue and operating margin as the primary financial metrics that we believe best represent our business performance.

Sheet Other Items
A1: Other Items
E2: Forecasted
A3: (in thousands) | B3: 2023 | C3: 2024 | D3: 2025 | E3: 2026 | F3: 2027 | G3: 2028 | H3: 2029
A4: Cost of Goods Sold | B4: ='P&L Input'!C4 -> 19715368 | C4: ='P&L Input'!D4 -> 21038464 | D4: ='P&L Input'!E4 -> 23275329
A5: Adjustment (See Note Below) | B5: 0 | C5: 0 | D5: -1116000
A6: COGS under normal business environment | B6: =SUM(B4:B5) -> 19715368 | C6: =SUM(C4:C5) -> 21038464 | D6: =SUM(D4:D5) -> 22159329
A7: as a % revenues | B7: =B6/'P&L Input'!C3 -> 0.5846216 | C7: =C6/'P&L Input'!D3 -> 0.53943443 | D7: =D6/'P&L Input'!E3 -> 0.49043471
A8: Increase % | C8: =(C6-B6)/B6 -> 0.067109881 | D8: =(D6-C6)/C6 -> 0.053276941
A9: Cost of revenues forecast based on normalized historical trends adjusted for expected operating leverage and scalability of streaming operations.
A10: The increase in cost of revenues for the year ended December 31, 2025 as compared to the year ended December 31, 2024 was primarily due to a $1,121 million increase in content amortization relating to our existing and new content, coupled with a $1,116 million increase in other cost of revenues, primarily driven by non-income tax assessments in Brazil. We do not expect that non-income taxes incurred in Brazil will materially impact our results of operations in future periods. See Note 9 Commitments and Contingencies in the accompanying notes to our consolidated financial statements for further detail on our non-income tax matters.
A12: Marketing | B12: ='P&L Input'!C6 -> 2657883 | C12: ='P&L Input'!D6 -> 2917554 | D12: ='P&L Input'!E6 -> 3301306
A13: as a % revenues | B13: =B12/'P&L Input'!C$3 -> 0.078814447 | C13: =C12/'P&L Input'!D$3 -> 0.074807224 | D13: =D12/'P&L Input'!E$3 -> 0.073065165
A14: Increase % | C14: =(C12-B12)/B12 -> 0.097698431 | D14: =(D12-C12)/C12 -> 0.1315321
A15: The increase in sales and marketing expenses for the year ended December 31, 2025 as compared to the year ended December 31, 2024 was primarily driven by a $222 million increase in marketing expenses, coupled with a $149 million increase in personnel-related costs due to the growth in advertising sales headcount.
A17: Technology and Development | B17: ='P&L Input'!C7 -> 2675758 | C17: ='P&L Input'!D7 -> 2925295 | D17: ='P&L Input'!E7 -> 3391390
A18: as a % revenues | B18: =B17/'P&L Input'!C$3 -> 0.079344496 | C18: =C17/'P&L Input'!D$3 -> 0.075005706 | D18: =D17/'P&L Input'!E$3 -> 0.075058923
A19: Increase % | C19: =(C17-B17)/B17 -> 0.093258434 | D19: =(D17-C17)/C17 -> 0.15933265
A20: The increase in technology and development expenses for the year ended December 31, 2025 as compared to the year ended December 31, 2024 was primarily due to a $438 million increase in personnel-related costs.
A22: General and Administrative | B22: ='P&L Input'!C8 -> 1720285 | C22: ='P&L Input'!D8 -> 1702039 | D22: ='P&L Input'!E8 -> 1888408
A23: as a % revenues | B23: =B22/'P&L Input'!C$3 -> 0.051011768 | C23: =C22/'P&L Input'!D$3 -> 0.043640945 | D23: =D22/'P&L Input'!E$3 -> 0.041794624
A24: Increase % | C24: =(C22-B22)/B22 -> -0.010606382 | D24: =(D22-C22)/C22 -> 0.10949749
A25: The increase in general and administrative expenses for the year ended December 31, 2025 as compared to the year ended December 31, 2024 was primarily due to a $92 million increase in personnel-related costs and a $64 million increase in third-party expenses. The increase in personnel-related costs was primarily driven by higher share-based compensation expense, while the increase in third-party expenses was attributable to higher legal fees and transaction-related costs, including those associated with the WBD transaction.
A27: Other Current assets | B27: ='Balance Sheet Input'!B8 -> 2780247 | C27: ='Balance Sheet Input'!C8 -> 3516640 | D27: ='Balance Sheet Input'!D8 -> 3957832
A28: as a % revenues | B28: =B27/'P&L Input'!C3 -> 0.082442918 | C28: =C27/'P&L Input'!D3 -> 0.090168023 | D28: =D27/'P&L Input'!E3 -> 0.08759553
A29: Increase % | C29: =(C27-B27)/B27 -> 0.26486604 | D29: =(D27-C27)/C27 -> 0.12545839
A30: Accounts Payable | B30: ='Balance Sheet Input'!B18 -> 747412 | C30: ='Balance Sheet Input'!C18 -> 899909 | D30: ='Balance Sheet Input'!D18 -> 900612
A31: Days Payable | B31: =(B30/B4)*365 -> 13.837194 | C31: =(C30/C4)*365 -> 15.612679 | D31: =(D30/D4)*365 -> 14.123254
A32: Increase % | C32: =(C30-B30)/B30 -> 0.20403338 | D32: =(D30-C30)/C30 -> 0.0007811901
A33: Accrued Expenses and other Liabilities | B33: ='Balance Sheet Input'!B19 -> 1803960 | C33: ='Balance Sheet Input'!C19 -> 2156544 | D33: ='Balance Sheet Input'!D19 -> 3220869
A34: as a % revenues | B34: =B33/'P&L Input'!C3 -> 0.05349299 | C34: =C33/'P&L Input'!D3 -> 0.05529463 | D34: =D33/'P&L Input'!E3 -> 0.071284918
A35: Increase % | C35: =(C33-B33)/B33 -> 0.19545001 | D35: =(D33-C33)/C33 -> 0.49353271
A36: Deferred Revenue | B36: ='Balance Sheet Input'!B20 -> 1442969 | C36: ='Balance Sheet Input'!C20 -> 1520813 | D36: ='Balance Sheet Input'!D20 -> 1775730
A37: as a % revenues | B37: =B36/'P&L Input'!C3 -> 0.042788491 | C37: =C36/'P&L Input'!D3 -> 0.038994239 | D37: =D36/'P&L Input'!E3 -> 0.039300812
A38: Increase % | C38: =(C36-B36)/B36 -> 0.053947105 | D38: =(D36-C36)/C36 -> 0.1676189
A39: Interest Expense | B39: ='P&L Input'!C11 -> -699826 | C39: ='P&L Input'!D11 -> -718733 | D39: ='P&L Input'!E11 -> -776510
A40: as a % revenues | B40: =B39/'P&L Input'!C$3 -> -0.020752004 | C40: =C39/'P&L Input'!D$3 -> -0.018428595 | D40: =D39/'P&L Input'!E$3 -> -0.017185875
A41: Increase % | C41: =(C39-B39)/B39 -> 0.027016716 | D41: =(D39-C39)/C39 -> 0.080387293
A42: Interest expense primarily consists of interest on our Notes of $716 million for the year ended December 31, 2025. The increase in interest expense for the year ended December 31, 2025 as compared to the year ended December 31, 2024 was primarily driven by higher amortization of debt issuance costs, including approximately $60 million related to financing arrangements entered into in connection with the WBD transaction. See Note 7 Debt for additional details regarding the financing arrangements associated with the WBD transaction.
A44: Interest and Other Income (Expense) | B44: ='P&L Input'!C12 -> -48772 | C44: ='P&L Input'!D12 -> 266776 | D44: ='P&L Input'!E12 -> 172459
A45: as a % revenues | B45: =B44/'P&L Input'!C$3 -> -0.0014462406 | C45: =C44/'P&L Input'!D$3 -> 0.0068402408 | D45: =D44/'P&L Input'!E$3 -> 0.0038168971
A46: Increase % | C46: =(C44-B44)/B44 -> -6.4698598 | D46: =(D44-C44)/C44 -> -0.3535438
A47: Interest and other income (expense) decreased for the year ended December 31, 2025, primarily due to foreign exchange losses of $123 million, net of the impacts of derivatives and hedging, compared to losses of $18 million for the corresponding period in 2024. In the year
A49: Provision for income taxes | B49: 797415 | C49: 1254026 | D49: 1741351
A50: Effective tax rate | B50: =B49/'P&L Input'!C13 -> 0.1285033 | C50: =C49/'P&L Input'!D13 -> 0.12583475 | D50: =D49/'P&L Input'!E13 -> 0.1368712
A52: The increase in our effective tax rate for the year ended December 31, 2025, as compared to the year ended December 31, 2024, is primarily due to a decrease in tax benefits associated with federal research and development tax credits as well as the growth in income before taxes exceeding the growth in excess tax benefits from stock-based compensation. See Note 11 Income Taxes to the consolidated financial statements for further information regarding income taxes.

Sheet Schedules
A1: PP&E
A3: (in thousands) | B3: 2023 | C3: 2024 | D3: 2025
A4: Beginning Balance | C4: =B7 -> 1491444 | D4: =C7 -> 1593756
A5: add: Capex | C5: =C7+C6-C4 -> 205891 | D5: =D7+D6-D4 -> 526304
A6: less: Depreciation | B6: 83157 | C6: 103579 | D6: 115710
A7: Closing Balance | B7: ='Balance Sheet Input'!B11 -> 1491444 | C7: ='Balance Sheet Input'!C11 -> 1593756 | D7: ='Balance Sheet Input'!D11 -> 2004350
A9: Useful life | C9: =(C4+C5)/C6 -> 16.386864 | D9: =(D4+D5)/D6 -> 18.322185
A12: Content Assets
A13: (in thousands) | B13: 2023 | C13: 2024 | D13: 2025
A14: Beginning Balance | C14: =B17 -> 31658056 | D14: =C17 -> 32452462
A15: add: Addition to Content Assets | C15: =C17+C16-C14 -> 10010653 | D15: =D17+D16-D14 -> 11132842
A16: less: Amortisation of Content Assets | C16: 9216247 | D16: 10806912
A17: Closing Balance | B17: ='Balance Sheet Input'!B10 -> 31658056 | C17: ='Balance Sheet Input'!C10 -> 32452462 | D17: ='Balance Sheet Input'!D10 -> 32778392
A19: Useful life | C19: =(C14+C15)/C16 -> 4.5212231 | D19: =(D14+D15)/D16 -> 4.0330951
A22: Debt Schedule
A23: Beginning Balance of Debt | C23: =B25 -> 14143417 | D23: =C25 -> 13798351
A24: add/less: Debt Taken /(debt repaid) | C24: =C25-C23 -> -345066 | D24: =D25-D23 -> -334380
A25: Closing Balance | B25: ='Balance Sheet Input'!B24 -> 14143417 | C25: ='Balance Sheet Input'!C24 -> 13798351 | D25: ='Balance Sheet Input'!D24 -> 13463971
A27: Interest Expense | B27: ='P&L Input'!C11 -> -699826 | C27: ='P&L Input'!D11 -> -718733 | D27: ='P&L Input'!E11 -> -776510
B28: =B27/B25 -> -0.049480688 | C28: =C27/C25 -> -0.052088326 | D28: =D27/D25 -> -0.057673178
A31: Content Assets, Net
A32: As of December 31, 2025, approximately $6,381 million, $2,280 million, and $1,469 million of the $12,139 million unamortized cost of the licensed content is expected to be amortized in each of the next three years. As of December 31, 2025, approximately $4,309 million, $2,784 million, and $1,840 million of the $10,687 million unamortized cost of the produced content that has been released is expected to be amortized in each of the next three years.
A34: Licensed content net | C34: 12422309 | D34: 12138578
A36: Produced content net
A37: Released less amort | C37: 10151543 | D37: 10687444
A38: in prod | C38: 9317367 | D38: 9210735
A39: in development and pre-prod | C39: 561243 | D39: 741635
C40: =SUM(C37:C39) -> 20030153 | D40: =SUM(D37:D39) -> 20639814
A42: Content assets, net | C42: =C34+C40 -> 32452462 | D42: =D34+D40 -> 32778392
A44: Amortisation | B44: 2023 | C44: 2024 | D44: 2025
A45: Licensed content | B45: 7145446 | C45: 7689014 | D45: 8713558
A46: Produced content | B46: 7051991 | C46: 7612503 | D46: 7708608
B47: =SUM(B45:B46) -> 14197437 | C47: =SUM(C45:C46) -> 15301517 | D47: =SUM(D45:D46) -> 16422166
A52: Content Assets
A53: (in thousands) | B53: 2023 | C53: 2024 | D53: 2025
A54: Beginning Balance | B54: =B56+B57 -> 45855493 | C54: =B57 -> 31658056 | D54: =C57 -> 32452462
A55: add: Addition to Content Assets | B55: =B57-B54+B56 -> 0 | C55: =C57-C54+C56 -> 16095923 | D55: =D57-D54+D56 -> 16748096
A56: less: Amortisation of Content Assets | B56: =B47 -> 14197437 | C56: =C47 -> 15301517 | D56: =D47 -> 16422166
A57: Closing Balance | B57: 31658056 | C57: =C42 -> 32452462 | D57: =D42 -> 32778392
A59: Useful life | D59: `
A62: Licensed content net
A63: Beginning Balance | B63: 12732549 | C63: =B66 -> 12722701 | D63: =C66 -> 12422309
A64: Additions | B64: =B66-B63+B65 -> 7135598 | C64: =C66-C63+C65 -> 7388622 | D64: =D66-D63+D65 -> 8429827
A65: Amortisation | B65: 7145446 | C65: =C87 -> 7689014 | D65: =D87 -> 8713558
A66: Closing Balance | B66: 12722701 | C66: 12422309 | D66: 12138578
A68: Produced content net
A69: Released | B69: =9483150+B88 -> 16535141 | C69: =10151543+C88 -> 17764046 | D69: =10687444+D88 -> 18396052
A70: in prod | B70: 8247578 | C70: 9317367 | D70: 9210735
A71: in development and pre-prod | B71: 844627 | C71: 561243 | D71: 741635
B72: =SUM(B69:B71) -> 25627346 | C72: =SUM(C69:C71) -> 27642656 | D72: =SUM(D69:D71) -> 28348422
A73: Less Amortisation | B73: =B88 -> 7051991 | C73: =C88 -> 7612503 | D73: =D88 -> 7708608
A74: Closing Balance | B74: =B72-B73 -> 18575355 | C74: =C72-C73 -> 20030153 | D74: =D72-D73 -> 20639814
A78: Content Assets
A79: Opening | B79: =B63+B72 -> 38359895 | C79: =C63+C72 -> 40365357 | D79: =D63+D72 -> 40770731
A80: Additions | B80: =B64 -> 7135598 | C80: =C64 -> 7388622 | D80: =D64 -> 8429827
A81: Amortisation | B81: =B65+B73 -> 14197437 | C81: =C65+C73 -> 15301517 | D81: =D65+D73 -> 16422166
A82: Closing Balance | B82: =B66+B74 -> 31298056 | C82: =C66+C74 -> 32452462 | D82: =D66+D74 -> 32778392
A86: Amortisation | B86: 2023 | C86: 2024 | D86: 2025
A87: Licensed content | B87: 7145446 | C87: 7689014 | D87: 8713558
A88: Produced content | B88: 7051991 | C88: 7612503 | D88: 7708608
B89: =SUM(B87:B88) -> 14197437 | C89: =SUM(C87:C88) -> 15301517 | D89: =SUM(D87:D88) -> 16422166
A93: Property and Equipment, Net
A95: Land | C95: 85000 | D95: 155664
A96: Buildings and improvements | C96: 475684 | D96: 537082 | E96: 30 Years
A97: Leasehold improvements | C97: 1026593 | D97: 1263051 | E97: Over the life od lease
A98: Furniture and fixtures | C98: 134987 | D98: 157984 | E98: 3 years
A99: Information technology | C99: 446419 | D99: 572407 | E99: 3-5 years
A100: Corporate aircraft | C100: 99175 | D100: 99164 | E100: 8-10 years
A101: Machinery and equipment | C101: 15135 | D101: 30879 | E101: 3-5 years
A102: Capital work-in-progress | C102: 228300 | D102: 285010
A103: Property and equipment, gross | C103: =SUM(C95:C102) -> 2511293 | D103: =SUM(D95:D102) -> 3101241
A104: Less: Accumulated depreciation | C104: -917537 | D104: -1096891
A105: Property and equipment, net | C105: =SUM(C103:C104) -> 1593756 | D105: =SUM(D103:D104) -> 2004350
A108: Leases
A109: Operating Lease cost | B109: 430856 | C109: 468282 | D109: 503637
A110: Short-term lease cost | B110: 207822 | C110: 197691 | D110: 207324
A111: Total Lease cost | B111: =SUM(B109:B110) -> 638678 | C111: =SUM(C109:C110) -> 665973 | D111: =SUM(D109:D110) -> 710961
A114: Operating lease right-of-use assets, net | C114: 2102310 | D114: 2207161
A116: Current operating lease liabilities | C116: 428482 | D116: 460475
A117: Non-current operating lease liabilities | C117: 1983688 | D117: 2052526
A118: Total operating lease liabilities | C118: =SUM(C116:C117) -> 2412170 | D118: =SUM(D116:D117) -> 2513001
A120: Weighted-average remaining lease term | C120: 6.9 years | D120: 7 years
A121: Weighted-average discount rate | C121: 0.035 | D121: 0.038
A124: Due in 12 month period ended december 31
A128: Cash and Cash Equivalents
A130: As of December 31, 2025 | B130: Amortized Cost | C130: Gross Unrealized Gains | D130: Gross Unrealized Losses | E130: Estimated Fair Value | F130: Cash & Cash Equivalents | G130: Short-term Investments | H130: Other Current Assets | I130: Non-current Assets
A131: Cash | B131: 5214163 | C131: 0 | D131: 0 | E131: 5214163 | F131: 5208710 | G131: - | H131: 5369 | I131: 84
A132: Level 1 securities:
A133: Money market funds | B133: 3259240 | C133: 0 | D133: 0 | E133: 3259240 | F133: 3259180 | G133: - | H133: - | I133: 60
A134: Level 2 securities:
A135: Time Deposits | B135: 594469 | C135: 0 | D135: 0 | E135: 594469 | F135: 565791 | G135: 28678 | H135: - | I135: -
A136: Total | B136: =SUM(B131:B135) -> 9067872 | C136: =SUM(C131:C135) -> 0 | D136: =SUM(D131:D135) -> 0 | E136: =SUM(E131:E135) -> 9067872 | F136: =SUM(F131:F135) -> 9033681 | G136: =SUM(G131:G135) -> 28678 | H136: =SUM(H131:H135) -> 5369 | I136: =SUM(I131:I135) -> 144
A138: As of December 31, 2024 | B138: Amortized Cost | C138: Gross Unrealized Gains | D138: Gross Unrealized Losses | E138: Estimated Fair Value | F138: Cash & Cash Equivalents | G138: Short-term Investments | H138: Other Current Assets | I138: Non-current Assets
A139: Cash | B139: 4866753 | C139: - | D139: - | E139: 4866753 | F139: 4864207 | G139: - | H139: 2472 | I139: 74
A140: Level 1 securities:
A141: Money market funds | B141: 2676314 | C141: - | D141: - | E141: 2676314 | F141: 2676256 | G141: - | H141: - | I141: 58
A142: Level 2 securities:
A143: Time Deposits | B143: 301374 | C143: - | D143: - | E143: 301374 | F143: 264270 | G143: 37104 | H143: - | I143: -
A144: Government securities | B144: 1738642 | C144: 3260 | D144: - | E144: 1741902 | F144: - | G144: 1741902 | H144: - | I144: -
A145: Total | B145: =SUM(B139:B144) -> 9583083 | C145: =SUM(C139:C144) -> 3260 | D145: =SUM(D139:D144) -> 0 | E145: =SUM(E139:E144) -> 9586343 | F145: =SUM(F139:F144) -> 7804733 | G145: =SUM(G139:G144) -> 1779006 | H145: =SUM(H139:H144) -> 2472 | I145: =SUM(I139:I144) -> 132
...

Sheet Debt
A1: Netflix, Inc. — Senior Notes Detail
A2: As of December 31, 2025 | US$ in thousands (euro face shown in €) | Source: FY2025 Form 10-K, Note 7 Debt (SEC accession 0001065280-26-000034, filed 2026-01-23)
A4: As of December 31, 2025, the Company had aggregate outstanding notes of $14,463 million, net of $56 million of issuance costs and discounts, with varying maturities (the “Notes”). As of December 31, 2024, the Company had aggregate outstanding notes of $15,583 million, net of $70 million of issuance costs and discounts. Each of the Notes are senior unsecured obligations of the Company. Interest is payable semi-annually at fixed rates. A portion of the outstanding Notes is denominated in foreign currency (comprised of €4,700 million) and is remeasured into U.S. dollars at each balance sheet date (with remeasurement loss, net of hedging impacts, totaling $72 million for the year ended December 31, 2025). See Note 8 Derivative Financial Instruments and Hedging Activities to the consolidated financial statements for further information regarding the Company’s derivative and non-derivative financial instruments.
A6: The following table provides a summary of the Company's outstanding debt and the fair values based on quoted market prices in less active markets as of December 31, 2025 and December 31, 2024:
B8: Principal Amount at Par
A9: Senior Notes | B9: Dec 31 2025 | C9: Dec 31 2026 | D9: Issuance Date | E9: Maturity | F9: Level 2 Fair Value (2025) | G9: Level 2 Fair Value (2024)
A10: 5.875% Senior Notes | B10: 0 | C10: 800 | D10: 42036 | E10: 45689 | F10: 0 | G10: 801
A11: 3.000% Senior Notes | B11: 0 | C11: 487 | D11: 43922 | E11: 45809 | F11: 0 | G11: 487
A12: 3.625% Senior Notes | B12: 0 | C12: 500 | D12: 43922 | E12: 45809 | F12: 0 | G12: 497
A13: 4.375% Senior Notes | B13: 1000 | C13: 1000 | D13: 42644 | E13: 46327 | F13: 1006 | G13: 998
A14: 3.625% Senior Notes | B14: 1526 | C14: 1346 | D14: 42856 | E14: 46508 | F14: 1550 | G14: 1375
A15: 4.875% Senior Notes | B15: 1600 | C15: 1600 | D15: 43009 | E15: 46844 | F15: 1634 | G15: 1607
A16: 5.875% Senior Notes | B16: 1900 | C16: 1900 | D16: 43191 | E16: 47058 | F16: 1998 | G16: 1970
A17: 4.625% Senior Notes | B17: 1292 | C17: 1139 | D17: 43374 | E17: 47239 | F17: 1363 | G17: 1220
A18: 6.375% Senior Notes | B18: 800 | C18: 800 | D18: 43374 | E18: 47239 | F18: 857 | G18: 848
A19: 3.875% Senior Notes | B19: 1409 | C19: 1242 | D19: 43556 | E19: 47423 | F19: 1455 | G19: 1293
A20: 5.375% Senior Notes | B20: 900 | C20: 900 | D20: 43556 | E20: 47423 | F20: 939 | G20: 918
A21: 3.625% Senior Notes | B21: 1292 | C21: 1139 | D21: 43739 | E21: 47635 | F21: 1322 | G21: 1174
... A24: 5.400% Senior Notes | B24: 800 | C24: 800 | D24: 45505 | E24: 56462 | F24: 777 | G24: 782
A25: Total | B25: =SUM(B10:B24) -> 14519 | C25: =SUM(C10:C24) -> 15653 | F25: =SUM(F10:F24) -> 14951 | G25: =SUM(G10:G24) -> 15948
A27: 1. The following Senior Notes have a principal amount denominated in Euro: 3.000% Senior Notes for €470 million, 3.625% Senior Notes for €1,300 million, 4.625% Senior Notes for €1,100 million, 3.875% Senior Notes for €1,200 million, and 3.625% Senior Notes for €1,100 million.
A28: In the year ended December 31, 2025, the Company repaid upon maturity the $800 million aggregate principal amount of its 5.875% Senior Notes, the €470 million aggregate principal amount of its 3.000% Senior Notes, and the $500 million aggregate principal amount of its 3.625% Senior Notes.
A29: Each of the Notes are repayable in whole or in part upon the occurrence of a change of control, at the option of the holders, at a purchase price in cash equal to 101% of the principal plus accrued interest. The Company may redeem the Notes prior to maturity in whole or in part at an amount equal to the principal amount thereof plus accrued and unpaid interest and an applicable premium. The Notes include, among other terms and conditions, limitations on the Company's ability to create, incur or allow certain liens, and consolidate or merge with, or convey, transfer or lease all or substantially all of the Company's and its subsidiaries assets, to another person. Certain of the Notes additionally limit the ability to enter into sale and lease-back transactions and create, assume, incur or guarantee additional indebtedness of certain of the Company's subsidiaries. As of December 31, 2025 and December 31, 2024, the Company was in compliance with all related covenants.
A32: EUR/USD year-end rate (assumption — confirm to 10-K): | D32: 1.176 | E32: <- adjust so euro USD-equivalents tie to Note 7
A34: Series (Senior Notes) | B34: Currency | C34: Coupon | D34: Face / Principal (in currency) | E34: Maturity Date | F34: Maturity Year | G34: Face in USD (computed) | H34: Fair Value (per 10-K)
A35: 4.375% Senior Notes | B35: USD | C35: 0.04375 | D35: 1000000 | E35: Nov 15, 2026 | F35: 2026 | G35: =IF(B35="EUR",D35*1.176,D35) -> 1000000 | H35: 1006000
A36: 3.625% Senior Notes | B36: EUR | C36: 0.03625 | D36: 1300000 | E36: May 15, 2027 | F36: 2027 | G36: =IF(B36="EUR",D36*1.176,D36) -> 1528800 | H36: 1550000
A37: 4.875% Senior Notes | B37: USD | C37: 0.04875 | D37: 1600000 | E37: Apr 15, 2028 | F37: 2028 | G37: =IF(B37="EUR",D37*1.176,D37) -> 1600000 | H37: 1634000
A38: 5.875% Senior Notes | B38: USD | C38: 0.05875 | D38: 1900000 | E38: Nov 15, 2028 | F38: 2028 | G38: =IF(B38="EUR",D38*1.176,D38) -> 1900000 | H38: 1998000
A39: 6.375% Senior Notes | B39: USD | C39: 0.06375 | D39: 800000 | E39: May 15, 2029 | F39: 2029 | G39: =IF(B39="EUR",D39*1.176,D39) -> 800000 | H39: 857000
A40: 4.625% Senior Notes | B40: EUR | C40: 0.04625 | D40: 1100000 | E40: May 15, 2029 | F40: 2029 | G40: =IF(B40="EUR",D40*1.176,D40) -> 1293600 | H40: 1363000
A41: 3.875% Senior Notes | B41: EUR | C41: 0.03875 | D41: 1200000 | E41: Nov 15, 2029 | F41: 2029 | G41: =IF(B41="EUR",D41*1.176,D41) -> 1411200 | H41: 1455000
A42: 5.375% Senior Notes | B42: USD | C42: 0.05375 | D42: 900000 | E42: Nov 15, 2029 | F42: 2029 | G42: =IF(B42="EUR",D42*1.176,D42) -> 900000 | H42: 939000
A43: 3.625% Senior Notes | B43: EUR | C43: 0.03625 | D43: 1100000 | E43: Jun 15, 2030 | F43: 2030 | G43: =IF(B43="EUR",D43*1.176,D43) -> 1293600 | H43: 1322000
A44: 4.875% Senior Notes | B44: USD | C44: 0.04875 | D44: 1000000 | E44: Jun 15, 2030 | F44: 2030 | G44: =IF(B44="EUR",D44*1.176,D44) -> 1000000 | H44: 1025000
A45: 4.90% Senior Notes | B45: USD | C45: 0.049 | D45: 1000000 | E45: Aug 15, 2034 | F45: 2034 | G45: =IF(B45="EUR",D45*1.176,D45) -> 1000000 | H45: 1025000
A46: 5.40% Senior Notes | B46: USD | C46: 0.054 | D46: 800000 | E46: Aug 15, 2054 | F46: 2054 | G46: =IF(B46="EUR",D46*1.176,D46) -> 800000 | H46: 777000
A47: Total aggregate principal | D47: =SUMIF(B35:B46,"USD",D35:D46) -> 9000000 | G47: =SUM(G35:G46) -> 14527200 | H47: =SUM(H35:H46) -> 14951000
A48: of which euro-denominated (€): | D48: =SUMIF(B35:B46,"EUR",D35:D46) -> 4700000
A50: Reconciliation to balance-sheet carrying amounts (per 10-K):
A51: Short-term debt (current portion) — 4.375% Notes due 2026, net | D51: 998865 | E51: Source: 10-K balance sheet / Note 7
A52: Long-term debt (non-current), net | D52: 13463971
A53: Total senior notes, net carrying amount | D53: =D51+D52 -> 14462836
A54: Total senior notes, fair value | D54: 14951000
A55: Weighted-average effective interest rate | D55: 0.0476 | E55: Source: 10-K Note 7 weighted-avg rate
A58: Debt — Current vs. Non-Current Classification
A59: US$ in thousands | Source: Netflix FY2025 Form 10-K, Consolidated Balance Sheet & Note 7
A61: Line item | B61: Dec 31, 2025 | C61: Dec 31, 2024 | D61: Note
A62: Short-term debt (current portion of senior notes) | B62: 998865 | C62: 1784453 | D62: Portion maturing within 12 months
A63: Long-term debt (senior notes, non-current) | B63: 13463971 | C63: 13798351 | D63: Maturing beyond 12 months
A64: Total senior notes, net carrying amount | B64: =SUM(B62:B63) -> 14462836 | C64: =SUM(C62:C63) -> 15582804
A66: % current | B66: =B62/B64 -> 0.069064255 | C66: =C62/C64 -> 0.11451424
A67: % non-current | B67: =B63/B64 -> 0.93093574 | C67: =C63/C64 -> 0.88548576
A70: Maturities of Debt — Aggregate Principal by Year
A71: Face / principal amounts | US$ in thousands (euro at year-end rate from Sheet 1) | Source: FY2025 10-K Note 7. Confirm USD-equivalent of euro tranches to the 10-K maturities table.
A73: Maturity Year | B73: USD-denominated principal | C73: Euro-denominated principal (€) | D73: Euro principal in USD (computed) | E73: Total principal in USD
A74: 2026 | B74: 1000000 | C74: 0 | D74: =C74*1.176 -> 0 | E74: =B74+D74 -> 1000000
A75: 2027 | B75: 0 | C75: 1300000 | D75: =C75*1.176 -> 1528800 | E75: =B75+D75 -> 1528800
A76: 2028 | B76: 3500000 | C76: 0 | D76: =C76*1.176 -> 0 | E76: =B76+D76 -> 3500000
A77: 2029 | B77: 1700000 | C77: 2300000 | D77: =C77*1.176 -> 2704800 | E77: =B77+D77 -> 4404800
A78: 2030 | B78: 1000000 | C78: 1100000 | D78: =C78*1.176 -> 1293600 | E78: =B78+D78 -> 2293600
A79: 2034 | B79: 1000000 | C79: 0 | D79: =C79*1.176 -> 0 | E79: =B79+D79 -> 1000000
A80: 2054 | B80: 800000 | C80: 0 | D80: =C80*1.176 -> 0 | E80: =B80+D80 -> 800000
A81: Total | B81: =SUM(B74:B80) -> 9000000 | C81: =SUM(C74:C80) -> 4700000 | D81: =SUM(D74:D80) -> 5527200 | E81: =SUM(E74:E80) -> 14527200
A83: Note: total principal differs from net carrying amount by unamortized debt discount/issuance costs and by euro remeasurement. Reconcile column E total to the 10-K Note 7 maturities table.
A85: Debt Rollforward — FY2025
A86: US$ in thousands | Net carrying amount. Endpoints verified to 10-K; component lines are flagged (yellow) to confirm to Note 7 / cash flow statement.
A88: Movement | B88: Amount | C88: Type | D88: Source / note
A89: Beginning balance — net carrying amount (Dec 31, 2024) | B89: 15582804 | C89: input | D89: FY2024 10-K (ST $1,784,453 + LT $13,798,351)
A90: Less: principal repaid at maturity during 2025 | B90: -1771000 | C90: input | D90: 2025 notes repaid: 5.875% $800M + 3.000% €470M + 3.625% $500M — confirm exact $ in Note 7
A91: Add: new issuances during 2025 | B91: 0 | C91: input | D91: Confirm — no new public notes identified in FY2025
A92: Add/(less): foreign-currency remeasurement of euro notes | B92: =B94-B89-SUM(B90:B91)-SUM(B93:B93) -> 651032 | C92: formula | D92: Non-cash euro remeasurement (plug to tie to ending balance)
A93: Add: amortization of debt discount & issuance costs | B93: 0 | C93: input | D93: Confirm to Note 7 / cash flow statement
A94: Ending balance — net carrying amount (Dec 31, 2025) | B94: 14462836 | D94: FY2025 10-K (ST $998,865 + LT $13,463,971)
A96: Check: rollforward sums to ending balance | B96: =B89+SUM(B90:B93)-B94 -> 0 | D96: Should equal 0
A99: Contractual Coupon Interest & Finance Cost — FY2025
A100: US$ in thousands | Contractual coupon computed from Sheet 1. GAAP interest expense (incl. amortization, net of capitalized interest) is a separate flagged input.
A102: Series | B102: Currency | C102: Coupon | D102: Face (in ccy) | E102: Annual coupon (USD, computed)
A103: 4.375% Senior Notes | B103: USD | C103: 0.04375 | D103: 1000000 | E103: =IF(B103="EUR",C103*D103*1.176,C103*D103) -> 43750
A104: 3.625% Senior Notes | B104: EUR | C104: 0.03625 | D104: 1300000 | E104: =IF(B104="EUR",C104*D104*1.176,C104*D104) -> 55419
A105: 4.875% Senior Notes | B105: USD | C105: 0.04875 | D105: 1600000 | E105: =IF(B105="EUR",C105*D105*1.176,C105*D105) -> 78000
A106: 5.875% Senior Notes | B106: USD | C106: 0.05875 | D106: 1900000 | E106: =IF(B106="EUR",C106*D106*1.176,C106*D106) -> 111625
A107: 6.375% Senior Notes | B107: USD | C107: 0.06375 | D107: 800000 | E107: =IF(B107="EUR",C107*D107*1.176,C107*D107) -> 51000
A108: 4.625% Senior Notes | B108: EUR | C108: 0.04625 | D108: 1100000 | E108: =IF(B108="EUR",C108*D108*1.176,C108*D108) -> 59829
A109: 3.875% Senior Notes | B109: EUR | C109: 0.03875 | D109: 1200000 | E109: =IF(B109="EUR",C109*D109*1.176,C109*D109) -> 54684
A110: 5.375% Senior Notes | B110: USD | C110: 0.05375 | D110: 900000 | E110: =IF(B110="EUR",C110*D110*1.176,C110*D110) -> 48375
A111: 3.625% Senior Notes | B111: EUR | C111: 0.03625 | D111: 1100000 | E111: =IF(B111="EUR",C111*D111*1.176,C111*D111) -> 46893
A112: 4.875% Senior Notes | B112: USD | C112: 0.04875 | D112: 1000000 | E112: =IF(B112="EUR",C112*D112*1.176,C112*D112) -> 48750
A113: 4.90% Senior Notes | B113: USD | C113: 0.049 | D113: 1000000 | E113: =IF(B113="EUR",C113*D113*1.176,C113*D113) -> 49000
A114: 5.40% Senior Notes | B114: USD | C114: 0.054 | D114: 800000 | E114: =IF(B114="EUR",C114*D114*1.176,C114*D114) -> 43200
A115: Total annual contractual coupon interest | E115: =SUM(E103:E114) -> 690525
A117: Reported figures — fill from FY2025 income statement / cash flow statement:
A118: Interest expense (income statement)
A119: Interest paid (cash flow statement)
A120: Capitalized interest (if any)
A122: Note: contractual coupon ≠ GAAP interest expense. Interest expense also reflects amortization of discount/issuance costs and any capitalized interest. Euro coupon converted at average-period rate in the actual filing; this model uses the year-end rate from Sheet 1 as an approximation.
A125: Sources, Legend & What to Confirm
A127: LEGEND: Blue text = hardcoded value verified from the 10-K / issuance filings. Black text = formula/calculation. Yellow fill = input to confirm against your own copy of the 10-K.
A129: VERIFIED DIRECTLY FROM FY2025 10-K (SEC accession 0001065280-26-000034, period 2025-12-31):
A130: - Short-term debt: $998,865K; Long-term debt: $13,463,971K; Total net carrying: $14,462,836K
...

Sheet Proj Drivers
A1: Projection Drivers — resolved from selected scenario
A3: (links into Assumptions tab via the scenario switch) | B3: 2025A | C3: 2026E | D3: 2027E | E3: 2028E | F3: 2029E | G3: 2030E
A5: Cost of revenues (% rev) | B5: =Assumptions!C50 -> 0.51513424 | C5: =Assumptions!D50 -> 0.512134 | D5: =Assumptions!E50 -> 0.509134 | E5: =Assumptions!F50 -> 0.506134 | F5: =Assumptions!G50 -> 0.503134 | G5: =Assumptions!H50 -> 0.500134
A6: Sales & marketing (% rev) | B6: =Assumptions!C58 -> 0.073065165 | C6: =Assumptions!D58 -> 0.072065 | D6: =Assumptions!E58 -> 0.071065 | E6: =Assumptions!F58 -> 0.070065 | F6: =Assumptions!G58 -> 0.069065 | G6: =Assumptions!H58 -> 0.068065
A7: Technology & dev (% rev) | B7: =Assumptions!C66 -> 0.075058923 | C7: =Assumptions!D66 -> 0.075059 | D7: =Assumptions!E66 -> 0.074059 | E7: =Assumptions!F66 -> 0.073059 | F7: =Assumptions!G66 -> 0.072059 | G7: =Assumptions!H66 -> 0.071059
A8: General & admin (% rev) | B8: =Assumptions!C74 -> 0.041794624 | C8: =Assumptions!D74 -> 0.040795 | D8: =Assumptions!E74 -> 0.039795 | E8: =Assumptions!F74 -> 0.038795 | F8: =Assumptions!G74 -> 0.037795 | G8: =Assumptions!H74 -> 0.036795
A9: Other current assets (% rev) | B9: =Assumptions!C82 -> 0.08759553 | C9: =Assumptions!D82 -> 0.087596 | D9: =Assumptions!E82 -> 0.086596 | E9: =Assumptions!F82 -> 0.085596 | F9: =Assumptions!G82 -> 0.084596 | G9: =Assumptions!H82 -> 0.083596
A10: Days payable outstanding | B10: =Assumptions!C90 -> 14.1 | C10: =Assumptions!D90 -> 14.2 | D10: =Assumptions!E90 -> 14.3 | E10: =Assumptions!F90 -> 14.4 | F10: =Assumptions!G90 -> 14.5 | G10: =Assumptions!H90 -> 14.5
A11: Accrued expenses (% rev) | B11: =Assumptions!C98 -> 0.071284918 | C11: =Assumptions!D98 -> 0.070285 | D11: =Assumptions!E98 -> 0.069285 | E11: =Assumptions!F98 -> 0.068285 | F11: =Assumptions!G98 -> 0.067285 | G11: =Assumptions!H98 -> 0.066285
A12: Deferred revenue (% rev) | B12: =Assumptions!C106 -> 0.039300812 | C12: =Assumptions!D106 -> 0.039301 | D12: =Assumptions!E106 -> 0.039301 | E12: =Assumptions!F106 -> 0.038301 | F12: =Assumptions!G106 -> 0.038301 | G12: =Assumptions!H106 -> 0.037301
A13: Interest & other income (expense) | B13: =Assumptions!C114 -> 172459 | C13: =Assumptions!D114 -> 50000 | D13: =Assumptions!E114 -> 75000 | E13: =Assumptions!F114 -> 100000 | F13: =Assumptions!G114 -> 100000 | G13: =Assumptions!H114 -> 125000
A14: Effective tax rate | B14: =Assumptions!C122 -> 0.1368712 | C14: =Assumptions!D122 -> 0.136871 | D14: =Assumptions!E122 -> 0.136871 | E14: =Assumptions!F122 -> 0.136871 | F14: =Assumptions!G122 -> 0.136871 | G14: =Assumptions!H122 -> 0.136871
A16: UCAN revenue growth | B16: =Assumptions!C10 -> 0.05 | C16: =Assumptions!D10 -> 0.05 | D16: =Assumptions!E10 -> 0.05 | E16: =Assumptions!F10 -> 0.05 | F16: =Assumptions!G10 -> 0.05 | G16: =Assumptions!H10 -> 0.05
A17: EMEA revenue growth | B17: =Assumptions!C18 -> 0.09 | C17: =Assumptions!D18 -> 0.09 | D17: =Assumptions!E18 -> 0.09 | E17: =Assumptions!F18 -> 0.09 | F17: =Assumptions!G18 -> 0.09 | G17: =Assumptions!H18 -> 0.09
A18: LATAM revenue growth | B18: =Assumptions!C26 -> 0.08 | C18: =Assumptions!D26 -> 0.08 | D18: =Assumptions!E26 -> 0.08 | E18: =Assumptions!F26 -> 0.08 | F18: =Assumptions!G26 -> 0.08 | G18: =Assumptions!H26 -> 0.08
A19: APAC revenue growth | B19: =Assumptions!C34 -> 0.12 | C19: =Assumptions!D34 -> 0.12 | D19: =Assumptions!E34 -> 0.12 | E19: =Assumptions!F34 -> 0.12 | F19: =Assumptions!G34 -> 0.12 | G19: =Assumptions!H34 -> 0.12
A20: Content spend growth | B20: =Assumptions!C42 -> 0.1 | C20: =Assumptions!D42 -> 0.1 | D20: =Assumptions!E42 -> 0.1 | E20: =Assumptions!F42 -> 0.1 | F20: =Assumptions!G42 -> 0.1 | G20: =Assumptions!H42 -> 0.1

Sheet Proj Schedules
A1: Projection Schedules — supporting builds
B3: 2025A | C3: 2026E | D3: 2027E | E3: 2028E | F3: 2029E | G3: 2030E
A4: Revenue Build
A5: United States & Canada (UCAN) | B5: ='Revenue Modelling'!$D$4 -> 19957152 | C5: =B5*(1+'Proj Drivers'!C16) -> 20955010 | D5: =C5*(1+'Proj Drivers'!D16) -> 22002760 | E5: =D5*(1+'Proj Drivers'!E16) -> 23102898 | F5: =E5*(1+'Proj Drivers'!F16) -> 24258043 | G5: =F5*(1+'Proj Drivers'!G16) -> 25470945
A6: Europe, Middle East & Africa (EMEA) | B6: ='Revenue Modelling'!$D$6 -> 14514646 | C6: =B6*(1+'Proj Drivers'!C17) -> 15820964 | D6: =C6*(1+'Proj Drivers'!D17) -> 17244851 | E6: =D6*(1+'Proj Drivers'!E17) -> 18796887 | F6: =E6*(1+'Proj Drivers'!F17) -> 20488607 | G6: =F6*(1+'Proj Drivers'!G17) -> 22332582
A7: Latin America (LATAM) | B7: ='Revenue Modelling'!$D$8 -> 5357521 | C7: =B7*(1+'Proj Drivers'!C18) -> 5786122.7 | D7: =C7*(1+'Proj Drivers'!D18) -> 6249012.5 | E7: =D7*(1+'Proj Drivers'!E18) -> 6748933.5 | F7: =E7*(1+'Proj Drivers'!F18) -> 7288848.2 | G7: =F7*(1+'Proj Drivers'!G18) -> 7871956
A8: Asia-Pacific (APAC) | B8: ='Revenue Modelling'!$D$10 -> 5353717 | C8: =B8*(1+'Proj Drivers'!C19) -> 5996163 | D8: =C8*(1+'Proj Drivers'!D19) -> 6715702.6 | E8: =D8*(1+'Proj Drivers'!E19) -> 7521586.9 | F8: =E8*(1+'Proj Drivers'!F19) -> 8424177.3 | G8: =F8*(1+'Proj Drivers'!G19) -> 9435078.6
A9: Total revenue | B9: =SUM(B5:B8) -> 45183036 | C9: =SUM(C5:C8) -> 48558259 | D9: =SUM(D5:D8) -> 52212326 | E9: =SUM(E5:E8) -> 56170306 | F9: =SUM(F5:F8) -> 60459676 | G9: =SUM(G5:G8) -> 65110562
A11: Content Assets Rollforward
A12: Opening balance | B12: ='Balance Sheet Input'!$C$10 -> 32452462 | C12: =B16 -> 32778392 | D12: =C16 -> 35195475 | E12: =D16 -> 38284644 | F12: =E16 -> 41897919 | G12: =F16 -> 45980117
A13: Additions to content assets | B13: =-'CFS Input'!$D$6 -> 17096617 | C13: =B13*(1+'Proj Drivers'!C20) -> 18806279 | D13: =C13*(1+'Proj Drivers'!D20) -> 20686907 | E13: =D13*(1+'Proj Drivers'!E20) -> 22755597 | F13: =E13*(1+'Proj Drivers'!F20) -> 25031157 | G13: =F13*(1+'Proj Drivers'!G20) -> 27534273
A14: Amortization of content assets | B14: ='CFS Input'!$D$8 -> 16422166 | C14: =C12*'Model Control'!$C$12 -> 16389196 | D14: =D12*'Model Control'!$C$12 -> 17597737 | E14: =E12*'Model Control'!$C$12 -> 19142322 | F14: =F12*'Model Control'!$C$12 -> 20948960 | G14: =G12*'Model Control'!$C$12 -> 22990058
A16: Closing balance, content assets net | B16: ='Balance Sheet Input'!$D$10 -> 32778392 | C16: =C12+C13-C14 -> 35195475 | D16: =D12+D13-D14 -> 38284644 | E16: =E12+E13-E14 -> 41897919 | F16: =F12+F13-F14 -> 45980117 | G16: =G12+G13-G14 -> 50524331
A18: Property & Equipment Rollforward
A19: Opening balance | B19: ='Balance Sheet Input'!$C$11 -> 1593756 | C19: =B22 -> 2004350 | D19: =C22 -> 2313445 | E19: =D22 -> 2612693.1 | F19: =E22 -> 2908712.9 | G19: =F22 -> 3207150.5
A20: Capital expenditure | B20: =-'CFS Input'!$D$23 -> 688220 | C20: =C9*'Model Control'!$C$10 -> 728373.89 | D20: =D9*'Model Control'!$C$10 -> 783184.89 | E20: =E9*'Model Control'!$C$10 -> 842554.59 | F20: =F9*'Model Control'!$C$10 -> 906895.14 | G20: =G9*'Model Control'!$C$10 -> 976658.43
A21: Depreciation | B21: =Schedules!$D$6 -> 115710 | C21: =C19*'Model Control'!$C$11 -> 419278.89 | D21: =D19*'Model Control'!$C$11 -> 483936.76 | E21: =E19*'Model Control'!$C$11 -> 546534.82 | F21: =F19*'Model Control'!$C$11 -> 608457.56 | G21: =G19*'Model Control'!$C$11 -> 670886.07
A22: Closing balance, PP&E net | B22: ='Balance Sheet Input'!$D$11 -> 2004350 | C22: =C19+C20-C21 -> 2313445 | D22: =D19+D20-D21 -> 2612693.1 | E22: =E19+E20-E21 -> 2908712.9 | F22: =F19+F20-F21 -> 3207150.5 | G22: =G19+G20-G21 -> 3512922.8
A24: Debt & Interest Schedule
A25: Total debt, opening | B25: ='Balance Sheet Input'!$C$21+'Balance Sheet Input'!$C$24 -> 15582804 | C25: =B28 -> 14462836 | D25: =C28 -> 13462836 | E25: =D28 -> 11936836 | F25: =E28 -> 8436836 | G25: =F28 -> 4035836
A26: Scheduled repayments (face, by maturity) | B26: =-'CFS Input'!$D$31 -> 1833450 | C26: 1000000 | D26: 1526000 | E26: 3500000 | F26: 4401000 | G26: 2292000
A27: New borrowings | B27: 0 | C27: 0 | D27: 0 | E27: 0 | F27: 0 | G27: 0
A28: Total debt, closing | B28: ='Balance Sheet Input'!$D$21+'Balance Sheet Input'!$D$24 -> 14462836 | C28: =C25-C26+C27 -> 13462836 | D28: =D25-D26+D27 -> 11936836 | E28: =E25-E26+E27 -> 8436836 | F28: =F25-F26+F27 -> 4035836 | G28: =G25-G26+G27 -> 1743836
A29: Current portion (next-year maturity) | B29: ='Balance Sheet Input'!$D$21 -> 998865 | C29: 1526000 | D29: 3500000 | E29: 4401000 | F29: 2292000 | G29: 0
A30: Long-term portion | B30: ='Balance Sheet Input'!$D$24 -> 13463971 | C30: =C28-C29 -> 11936836 | D30: =D28-D29 -> 8436836 | E30: =E28-E29 -> 4035836 | F30: =F28-F29 -> 1743836 | G30: =G28-G29 -> 1743836
A31: Average debt | B31: =AVERAGE(B25,B28) -> 15022820 | C31: =AVERAGE(C25,C28) -> 13962836 | D31: =AVERAGE(D25,D28) -> 12699836 | E31: =AVERAGE(E25,E28) -> 10186836 | F31: =AVERAGE(F25,F28) -> 6236336 | G31: =AVERAGE(G25,G28) -> 2889836
A32: Interest expense | B32: =-'P&L Input'!$E$11 -> 776510 | C32: =C31*'Model Control'!$C$19 -> 664630.99 | D32: =D31*'Model Control'!$C$19 -> 604512.19 | E32: =E31*'Model Control'!$C$19 -> 484893.39 | F32: =F31*'Model Control'!$C$19 -> 296849.59 | G32: =G31*'Model Control'!$C$19 -> 137556.19
A34: Balance Sheet Driver Schedule
A35: Other current assets | B35: ='Balance Sheet Input'!$D$8 -> 3957832 | C35: =C9*'Proj Drivers'!C9 -> 4253509.3 | D35: =D9*'Proj Drivers'!D9 -> 4521378.6 | E35: =E9*'Proj Drivers'!E9 -> 4807953.5 | F35: =F9*'Proj Drivers'!F9 -> 5114646.7 | G35: =G9*'Proj Drivers'!G9 -> 5442982.5
A36: Accounts payable (DPO basis) | B36: ='Balance Sheet Input'!$D$18 -> 900612 | C36: ='Proj Drivers'!C10/365*(C9*'Proj Drivers'!C5) -> 967480.46 | D36: ='Proj Drivers'!D10/365*(D9*'Proj Drivers'!D5) -> 1041473.7 | E36: ='Proj Drivers'!E10/365*(E9*'Proj Drivers'!E5) -> 1121610.1 | F36: ='Proj Drivers'!F10/365*(F9*'Proj Drivers'!F5) -> 1208438.7 | G36: ='Proj Drivers'!G10/365*(G9*'Proj Drivers'!G5) -> 1293638.6
A37: Accrued expenses & other liabilities | B37: ='Balance Sheet Input'!$D$19 -> 3220869 | C37: =C9*'Proj Drivers'!C11 -> 3412917.3 | D37: =D9*'Proj Drivers'!D11 -> 3617531 | E37: =E9*'Proj Drivers'!E11 -> 3835589.3 | F37: =F9*'Proj Drivers'!F11 -> 4068029.3 | G37: =G9*'Proj Drivers'!G11 -> 4315853.6
A38: Deferred revenue | B38: ='Balance Sheet Input'!$D$20 -> 1775730 | C38: =C9*'Proj Drivers'!C12 -> 1908388.2 | D38: =D9*'Proj Drivers'!D12 -> 2051996.6 | E38: =E9*'Proj Drivers'!E12 -> 2151378.9 | F38: =F9*'Proj Drivers'!F12 -> 2315666 | G38: =G9*'Proj Drivers'!G12 -> 2428689.1
A39: Current content liabilities | B39: ='Balance Sheet Input'!$D$17 -> 4084854 | C39: =C9*'Model Control'!$C$13 -> 4370243.4 | D39: =D9*'Model Control'!$C$13 -> 4699109.3 | E39: =E9*'Model Control'!$C$13 -> 5055327.5 | F39: =F9*'Model Control'!$C$13 -> 5441370.8 | G39: =G9*'Model Control'!$C$13 -> 5859950.6
A40: Non-current content liabilities | B40: ='Balance Sheet Input'!$D$23 -> 1579476 | C40: =C9*'Model Control'!$C$14 -> 1699539.1 | D40: =D9*'Model Control'!$C$14 -> 1827431.4 | E40: =E9*'Model Control'!$C$14 -> 1965960.7 | F40: =F9*'Model Control'!$C$14 -> 2116088.7 | G40: =G9*'Model Control'!$C$14 -> 2278869.7
A41: Other non-current assets | B41: ='Balance Sheet Input'!$D$12 -> 7794060 | C41: =C9*'Model Control'!$C$15 -> 8376299.8 | D41: =D9*'Model Control'!$C$15 -> 9006626.3 | E41: =E9*'Model Control'!$C$15 -> 9689377.8 | F41: =F9*'Model Control'!$C$15 -> 10429294 | G41: =G9*'Model Control'!$C$15 -> 11231572
A42: Other non-current liabilities | B42: ='Balance Sheet Input'!$D$25 -> 2957128 | C42: =C9*'Model Control'!$C$16 -> 3180566 | D42: =D9*'Model Control'!$C$16 -> 3419907.4 | E42: =E9*'Model Control'!$C$16 -> 3679155 | F42: =F9*'Model Control'!$C$16 -> 3960108.8 | G42: =G9*'Model Control'!$C$16 -> 4264741.8
A43: Short-term investments | B43: ='Balance Sheet Input'!$D$7 -> 28678 | C43: ='Model Control'!$C$20 -> 28678 | D43: ='Model Control'!$C$20 -> 28678 | E43: ='Model Control'!$C$20 -> 28678 | F43: ='Model Control'!$C$20 -> 28678 | G43: ='Model Control'!$C$20 -> 28678
A45: Equity Rollforward
A46: Stock-based compensation | B46: ='CFS Input'!$D$10 -> 368449 | C46: =C9*'Model Control'!$C$17 -> 398177.73 | D46: =D9*'Model Control'!$C$17 -> 428141.07 | E46: =E9*'Model Control'!$C$17 -> 460596.51 | F46: =F9*'Model Control'!$C$17 -> 495769.34 | G46: =G9*'Model Control'!$C$17 -> 533906.61
A47: Stock issuance proceeds | B47: ='CFS Input'!$D$32 -> 666965 | C47: =C9*'Model Control'!$C$18 -> 718662.24 | D47: =D9*'Model Control'!$C$18 -> 772742.43 | E47: =E9*'Model Control'!$C$18 -> 831320.53 | F47: =F9*'Model Control'!$C$18 -> 894803.2 | G47: =G9*'Model Control'!$C$18 -> 963636.32
A48: Share repurchases | B48: =-'CFS Input'!$D$33 -> 9127167 | C48: ='Model Control'!C23 -> 9127167 | D48: ='Model Control'!D23 -> 9127167 | E48: ='Model Control'!E23 -> 9127167 | F48: ='Model Control'!F23 -> 9127167 | G48: ='Model Control'!G23 -> 9127167
A49: Common stock, closing | B49: ='Balance Sheet Input'!$D$28 -> 7286410 | C49: =B49+C46+C47 -> 8403250 | D49: =C49+D46+D47 -> 9604133.5 | E49: =D49+E46+E47 -> 10896051 | F49: =E49+F46+F47 -> 12286623 | G49: =F49+G46+G47 -> 13784166
A50: Treasury stock, closing | B50: ='Balance Sheet Input'!$D$29 -> -22372658 | C50: =B50-C48 -> -31499825 | D50: =C50-D48 -> -40626992 | E50: =D50-E48 -> -49754159 | F50: =E50-F48 -> -58881326 | G50: =F50-G48 -> -68008493
A51: AOCI, closing | B51: ='Balance Sheet Input'!$D$30 -> -580382 | C51: =B51 -> -580382 | D51: =C51 -> -580382 | E51: =D51 -> -580382 | F51: =E51 -> -580382 | G51: =F51 -> -580382
A52: Retained earnings, closing | B52: ='Balance Sheet Input'!$D$31 -> 42282118 | C52: =B52+'Projected PnL'!C13 -> 54323003 | D52: =C52+'Projected PnL'!D13 -> 67653765 | E52: =D52+'Projected PnL'!E13 -> 82445436 | F52: =E52+'Projected PnL'!F13 -> 98867434 | G52: =F52+'Projected PnL'!G13 -> 1.1706203e+08

Sheet Projected PnL
A1: Netflix, Inc. — Projected Income Statement
A2: =CONCATENATE("Scenario: ",'Model Control'!$C$4) -> Scenario: Neutral Case
B3: 2025A | C3: 2026E | D3: 2027E | E3: 2028E | F3: 2029E | G3: 2030E
A4: Revenues | B4: ='P&L Input'!$E$3 -> 45183036 | C4: ='Proj Schedules'!C9 -> 48558259 | D4: ='Proj Schedules'!D9 -> 52212326 | E4: ='Proj Schedules'!E9 -> 56170306 | F4: ='Proj Schedules'!F9 -> 60459676 | G4: ='Proj Schedules'!G9 -> 65110562
A5: Cost of revenues | B5: ='P&L Input'!$E$4 -> 23275329 | C5: ='Proj Schedules'!C9*'Proj Drivers'!C5 -> 24868336 | D5: ='Proj Schedules'!D9*'Proj Drivers'!D5 -> 26583070 | E5: ='Proj Schedules'!E9*'Proj Drivers'!E5 -> 28429702 | F5: ='Proj Schedules'!F9*'Proj Drivers'!F5 -> 30419319 | G5: ='Proj Schedules'!G9*'Proj Drivers'!G5 -> 32564006
A6: Gross profit | B6: =B4-B5 -> 21907707 | C6: =C4-C5 -> 23689924 | D6: =D4-D5 -> 25629256 | E6: =E4-E5 -> 27740604 | F6: =F4-F5 -> 30040357 | G6: =G4-G5 -> 32546556
A7: Sales and marketing | B7: ='P&L Input'!$E$6 -> 3301306 | C7: ='Proj Schedules'!C9*'Proj Drivers'!C6 -> 3499351 | D7: ='Proj Schedules'!D9*'Proj Drivers'!D6 -> 3710469 | E7: ='Proj Schedules'!E9*'Proj Drivers'!E6 -> 3935572.5 | F7: ='Proj Schedules'!F9*'Proj Drivers'!F6 -> 4175647.5 | G7: ='Proj Schedules'!G9*'Proj Drivers'!G6 -> 4431750.4
A8: Technology and development | B8: ='P&L Input'!$E$7 -> 3391390 | C8: ='Proj Schedules'!C9*'Proj Drivers'!C7 -> 3644734.4 | D8: ='Proj Schedules'!D9*'Proj Drivers'!D7 -> 3866792.7 | E8: ='Proj Schedules'!E9*'Proj Drivers'!E7 -> 4103746.4 | F8: ='Proj Schedules'!F9*'Proj Drivers'!F7 -> 4356663.8 | G8: ='Proj Schedules'!G9*'Proj Drivers'!G7 -> 4626691.4
A9: General and administrative | B9: ='P&L Input'!$E$8 -> 1888408 | C9: ='Proj Schedules'!C9*'Proj Drivers'!C8 -> 1980934.2 | D9: ='Proj Schedules'!D9*'Proj Drivers'!D8 -> 2077789.5 | E9: ='Proj Schedules'!E9*'Proj Drivers'!E8 -> 2179127 | F9: ='Proj Schedules'!F9*'Proj Drivers'!F8 -> 2285073.4 | G9: ='Proj Schedules'!G9*'Proj Drivers'!G8 -> 2395743.1
A10: Operating income | B10: =B6-B7-B8-B9 -> 13326603 | C10: =C6-C7-C8-C9 -> 14564904 | D10: =D6-D7-D8-D9 -> 15974205 | E10: =E6-E7-E8-E9 -> 17522158 | F10: =F6-F7-F8-F9 -> 19222973 | G10: =G6-G7-G8-G9 -> 21092371
A11: Interest expense | B11: ='P&L Input'!$E$11 -> -776510 | C11: =-'Proj Schedules'!C32 -> -664630.99 | D11: =-'Proj Schedules'!D32 -> -604512.19 | E11: =-'Proj Schedules'!E32 -> -484893.39 | F11: =-'Proj Schedules'!F32 -> -296849.59 | G11: =-'Proj Schedules'!G32 -> -137556.19
A12: Interest and other income (expense) | B12: ='P&L Input'!$E$12 -> 172459 | C12: ='Proj Drivers'!C13 -> 50000 | D12: ='Proj Drivers'!D13 -> 75000 | E12: ='Proj Drivers'!E13 -> 100000 | F12: ='Proj Drivers'!F13 -> 100000 | G12: ='Proj Drivers'!G13 -> 125000
A13: Net income | B13: =B17+B18 -> 10981201 | C13: =C17+C18 -> 12040885 | D13: =D17+D18 -> 13330762 | E13: =E17+E18 -> 14791670 | F13: =F17+F18 -> 16421998 | G13: =G17+G18 -> 18194600
A15: Operating margin | B15: =B10/B4 -> 0.29494705 | C15: =C10/C4 -> 0.299947 | D15: =D10/D4 -> 0.305947 | E15: =E10/E4 -> 0.311947 | F15: =F10/F4 -> 0.317947 | G15: =G10/G4 -> 0.323947
A16: Net margin | B16: =B13/B4 -> 0.24303814 | C16: =C13/C4 -> 0.24796781 | D16: =D13/D4 -> 0.25531829 | E16: =E13/E4 -> 0.26333612 | F16: =F13/F4 -> 0.27161903 | G16: =G13/G4 -> 0.2794416
A17: Income before income taxes (EBT) | B17: =B10+B11+B12 -> 12722552 | C17: =C10+C11+C12 -> 13950273 | D17: =D10+D11+D12 -> 15444692 | E17: =E10+E11+E12 -> 17137265 | F17: =F10+F11+F12 -> 19026123 | G17: =G10+G11+G12 -> 21079815
A18: Provision for income taxes | B18: ='P&L Input'!$E$14 -> -1741351 | C18: =-C17*'Proj Drivers'!C14 -> -1909387.9 | D18: =-D17*'Proj Drivers'!D14 -> -2113930.5 | E18: =-E17*'Proj Drivers'!E14 -> -2345594.6 | F18: =-F17*'Proj Drivers'!F14 -> -2604124.5 | G18: =-G17*'Proj Drivers'!G14 -> -2885215.4

Sheet Projected BS
A1: Netflix, Inc. — Projected Balance Sheet
B3: 2025A | C3: 2026E | D3: 2027E | E3: 2028E | F3: 2029E | G3: 2030E
A4: Assets
A5: Cash and cash equivalents | B5: ='Balance Sheet Input'!$D$6 -> 9033681 | C5: ='Projected CFS'!C32 -> 9480609.9 | D5: ='Projected CFS'!D32 -> 10190790 | E5: ='Projected CFS'!E32 -> 9920161.5 | F5: ='Projected CFS'!F32 -> 10078002 | G5: ='Projected CFS'!G32 -> 13702418
A6: Short-term investments | B6: ='Balance Sheet Input'!$D$7 -> 28678 | C6: ='Proj Schedules'!C43 -> 28678 | D6: ='Proj Schedules'!D43 -> 28678 | E6: ='Proj Schedules'!E43 -> 28678 | F6: ='Proj Schedules'!F43 -> 28678 | G6: ='Proj Schedules'!G43 -> 28678
A7: Other current assets | B7: ='Balance Sheet Input'!$D$8 -> 3957832 | C7: ='Proj Schedules'!C35 -> 4253509.3 | D7: ='Proj Schedules'!D35 -> 4521378.6 | E7: ='Proj Schedules'!E35 -> 4807953.5 | F7: ='Proj Schedules'!F35 -> 5114646.7 | G7: ='Proj Schedules'!G35 -> 5442982.5
A8: Total current assets | B8: =SUM(B5:B7) -> 13020191 | C8: =SUM(C5:C7) -> 13762797 | D8: =SUM(D5:D7) -> 14740847 | E8: =SUM(E5:E7) -> 14756793 | F8: =SUM(F5:F7) -> 15221326 | G8: =SUM(G5:G7) -> 19174078
A9: Content assets, net | B9: ='Balance Sheet Input'!$D$10 -> 32778392 | C9: ='Proj Schedules'!C16 -> 35195475 | D9: ='Proj Schedules'!D16 -> 38284644 | E9: ='Proj Schedules'!E16 -> 41897919 | F9: ='Proj Schedules'!F16 -> 45980117 | G9: ='Proj Schedules'!G16 -> 50524331
A10: Property and equipment, net | B10: ='Balance Sheet Input'!$D$11 -> 2004350 | C10: ='Proj Schedules'!C22 -> 2313445 | D10: ='Proj Schedules'!D22 -> 2612693.1 | E10: ='Proj Schedules'!E22 -> 2908712.9 | F10: ='Proj Schedules'!F22 -> 3207150.5 | G10: ='Proj Schedules'!G22 -> 3512922.8
A11: Other non-current assets | B11: ='Balance Sheet Input'!$D$12 -> 7794060 | C11: ='Proj Schedules'!C41 -> 8376299.8 | D11: ='Proj Schedules'!D41 -> 9006626.3 | E11: ='Proj Schedules'!E41 -> 9689377.8 | F11: ='Proj Schedules'!F41 -> 10429294 | G11: ='Proj Schedules'!G41 -> 11231572
A12: Total assets | B12: =B8+B9+B10+B11 -> 55596993 | C12: =C8+C9+C10+C11 -> 59648017 | D12: =D8+D9+D10+D11 -> 64644810 | E12: =E8+E9+E10+E11 -> 69252803 | F12: =F8+F9+F10+F11 -> 74837888 | G12: =G8+G9+G10+G11 -> 84442904
A14: Liabilities and Stockholders' Equity
A15: Current content liabilities | B15: ='Balance Sheet Input'!$D$17 -> 4084854 | C15: ='Proj Schedules'!C39 -> 4370243.4 | D15: ='Proj Schedules'!D39 -> 4699109.3 | E15: ='Proj Schedules'!E39 -> 5055327.5 | F15: ='Proj Schedules'!F39 -> 5441370.8 | G15: ='Proj Schedules'!G39 -> 5859950.6
A16: Accounts payable | B16: ='Balance Sheet Input'!$D$18 -> 900612 | C16: ='Proj Schedules'!C36 -> 967480.46 | D16: ='Proj Schedules'!D36 -> 1041473.7 | E16: ='Proj Schedules'!E36 -> 1121610.1 | F16: ='Proj Schedules'!F36 -> 1208438.7 | G16: ='Proj Schedules'!G36 -> 1293638.6
A17: Accrued expenses and other liabilities | B17: ='Balance Sheet Input'!$D$19 -> 3220869 | C17: ='Proj Schedules'!C37 -> 3412917.3 | D17: ='Proj Schedules'!D37 -> 3617531 | E17: ='Proj Schedules'!E37 -> 3835589.3 | F17: ='Proj Schedules'!F37 -> 4068029.3 | G17: ='Proj Schedules'!G37 -> 4315853.6
A18: Deferred revenue | B18: ='Balance Sheet Input'!$D$20 -> 1775730 | C18: ='Proj Schedules'!C38 -> 1908388.2 | D18: ='Proj Schedules'!D38 -> 2051996.6 | E18: ='Proj Schedules'!E38 -> 2151378.9 | F18: ='Proj Schedules'!F38 -> 2315666 | G18: ='Proj Schedules'!G38 -> 2428689.1
A19: Short-term debt | B19: ='Balance Sheet Input'!$D$21 -> 998865 | C19: ='Proj Schedules'!C29 -> 1526000 | D19: ='Proj Schedules'!D29 -> 3500000 | E19: ='Proj Schedules'!E29 -> 4401000 | F19: ='Proj Schedules'!F29 -> 2292000 | G19: ='Proj Schedules'!G29 -> 0
A20: Total current liabilities | B20: =SUM(B15:B19) -> 10980930 | C20: =SUM(C15:C19) -> 12185029 | D20: =SUM(D15:D19) -> 14910111 | E20: =SUM(E15:E19) -> 16564906 | F20: =SUM(F15:F19) -> 15325505 | G20: =SUM(G15:G19) -> 13898132
A21: Non-current content liabilities | B21: ='Balance Sheet Input'!$D$23 -> 1579476 | C21: ='Proj Schedules'!C40 -> 1699539.1 | D21: ='Proj Schedules'!D40 -> 1827431.4 | E21: ='Proj Schedules'!E40 -> 1965960.7 | F21: ='Proj Schedules'!F40 -> 2116088.7 | G21: ='Proj Schedules'!G40 -> 2278869.7
A22: Long-term debt | B22: ='Balance Sheet Input'!$D$24 -> 13463971 | C22: ='Proj Schedules'!C30 -> 11936836 | D22: ='Proj Schedules'!D30 -> 8436836 | E22: ='Proj Schedules'!E30 -> 4035836 | F22: ='Proj Schedules'!F30 -> 1743836 | G22: ='Proj Schedules'!G30 -> 1743836
A23: Other non-current liabilities | B23: ='Balance Sheet Input'!$D$25 -> 2957128 | C23: ='Proj Schedules'!C42 -> 3180566 | D23: ='Proj Schedules'!D42 -> 3419907.4 | E23: ='Proj Schedules'!E42 -> 3679155 | F23: ='Proj Schedules'!F42 -> 3960108.8 | G23: ='Proj Schedules'!G42 -> 4264741.8
A24: Total liabilities | B24: =B20+B21+B22+B23 -> 28981505 | C24: =C20+C21+C22+C23 -> 29001970 | D24: =D20+D21+D22+D23 -> 28594285 | E24: =E20+E21+E22+E23 -> 26245858 | F24: =F20+F21+F22+F23 -> 23145538 | G24: =G20+G21+G22+G23 -> 22185579
A26: Common stock | B26: ='Balance Sheet Input'!$D$28 -> 7286410 | C26: ='Proj Schedules'!C49 -> 8403250 | D26: ='Proj Schedules'!D49 -> 9604133.5 | E26: ='Proj Schedules'!E49 -> 10896051 | F26: ='Proj Schedules'!F49 -> 12286623 | G26: ='Proj Schedules'!G49 -> 13784166
A27: Treasury stock | B27: ='Balance Sheet Input'!$D$29 -> -22372658 | C27: ='Proj Schedules'!C50 -> -31499825 | D27: ='Proj Schedules'!D50 -> -40626992 | E27: ='Proj Schedules'!E50 -> -49754159 | F27: ='Proj Schedules'!F50 -> -58881326 | G27: ='Proj Schedules'!G50 -> -68008493
A28: Accumulated other comprehensive income (loss) | B28: ='Balance Sheet Input'!$D$30 -> -580382 | C28: ='Proj Schedules'!C51 -> -580382 | D28: ='Proj Schedules'!D51 -> -580382 | E28: ='Proj Schedules'!E51 -> -580382 | F28: ='Proj Schedules'!F51 -> -580382 | G28: ='Proj Schedules'!G51 -> -580382
A29: Retained earnings | B29: ='Balance Sheet Input'!$D$31 -> 42282118 | C29: ='Proj Schedules'!C52 -> 54323003 | D29: ='Proj Schedules'!D52 -> 67653765 | E29: ='Proj Schedules'!E52 -> 82445436 | F29: ='Proj Schedules'!F52 -> 98867434 | G29: ='Proj Schedules'!G52 -> 1.1706203e+08
A30: Total stockholders' equity | B30: =SUM(B26:B29) -> 26615488 | C30: =SUM(C26:C29) -> 30646046 | D30: =SUM(D26:D29) -> 36050525 | E30: =SUM(E26:E29) -> 43006945 | F30: =SUM(F26:F29) -> 51692349 | G30: =SUM(G26:G29) -> 62257325
A31: Total liabilities and equity | B31: =B24+B30 -> 55596993 | C31: =C24+C30 -> 59648017 | D31: =D24+D30 -> 64644810 | E31: =E24+E30 -> 69252803 | F31: =F24+F30 -> 74837888 | G31: =G24+G30 -> 84442904
A33: CHECK: Assets - Liabilities & Equity (must be 0) | B33: =B12-B31 -> 0 | C33: =C12-C31 -> 0 | D33: =D12-D31 -> 0 | E33: =E12-E31 -> 0 | F33: =F12-F31 -> 0 | G33: =G12-G31 -> 0

Sheet Projected CFS
A1: Netflix, Inc. — Projected Cash Flow Statement (Indirect)
C3: 2026E | D3: 2027E | E3: 2028E | F3: 2029E | G3: 2030E
A4: Cash flows from operating activities
A5: Net income | C5: ='Projected PnL'!C13 -> 12040885 | D5: ='Projected PnL'!D13 -> 13330762 | E5: ='Projected PnL'!E13 -> 14791670 | F5: ='Projected PnL'!F13 -> 16421998 | G5: ='Projected PnL'!G13 -> 18194600
A6: Depreciation | C6: ='Proj Schedules'!C21 -> 419278.89 | D6: ='Proj Schedules'!D21 -> 483936.76 | E6: ='Proj Schedules'!E21 -> 546534.82 | F6: ='Proj Schedules'!F21 -> 608457.56 | G6: ='Proj Schedules'!G21 -> 670886.07
A7: Amortization of content assets | C7: ='Proj Schedules'!C14 -> 16389196 | D7: ='Proj Schedules'!D14 -> 17597737 | E7: ='Proj Schedules'!E14 -> 19142322 | F7: ='Proj Schedules'!F14 -> 20948960 | G7: ='Proj Schedules'!G14 -> 22990058
A8: Additions to content assets | C8: =-'Proj Schedules'!C13 -> -18806279 | D8: =-'Proj Schedules'!D13 -> -20686907 | E8: =-'Proj Schedules'!E13 -> -22755597 | F8: =-'Proj Schedules'!F13 -> -25031157 | G8: =-'Proj Schedules'!G13 -> -27534273
A9: Change in content liabilities | C9: =('Proj Schedules'!C39+'Proj Schedules'!C40)-('Proj Schedules'!B39+'Proj Schedules'!B40) -> 405452.43 | D9: =('Proj Schedules'!D39+'Proj Schedules'!D40)-('Proj Schedules'!C39+'Proj Schedules'!C40) -> 456758.33 | E9: =('Proj Schedules'!E39+'Proj Schedules'!E40)-('Proj Schedules'!D39+'Proj Schedules'!D40) -> 494747.49 | F9: =('Proj Schedules'!F39+'Proj Schedules'!F40)-('Proj Schedules'!E39+'Proj Schedules'!E40) -> 536171.24 | G9: =('Proj Schedules'!G39+'Proj Schedules'!G40)-('Proj Schedules'!F39+'Proj Schedules'!F40) -> 581360.74
A10: Stock-based compensation | C10: ='Proj Schedules'!C46 -> 398177.73 | D10: ='Proj Schedules'!D46 -> 428141.07 | E10: ='Proj Schedules'!E46 -> 460596.51 | F10: ='Proj Schedules'!F46 -> 495769.34 | G10: ='Proj Schedules'!G46 -> 533906.61
A11: Change in other current assets | C11: =-('Proj Schedules'!C35-'Proj Schedules'!B35) -> -295677.3 | D11: =-('Proj Schedules'!D35-'Proj Schedules'!C35) -> -267869.29 | E11: =-('Proj Schedules'!E35-'Proj Schedules'!D35) -> -286574.92 | F11: =-('Proj Schedules'!F35-'Proj Schedules'!E35) -> -306693.23 | G11: =-('Proj Schedules'!G35-'Proj Schedules'!F35) -> -328335.79
A12: Change in accounts payable | C12: ='Proj Schedules'!C36-'Proj Schedules'!B36 -> 66868.455 | D12: ='Proj Schedules'!D36-'Proj Schedules'!C36 -> 73993.263 | E12: ='Proj Schedules'!E36-'Proj Schedules'!D36 -> 80136.429 | F12: ='Proj Schedules'!F36-'Proj Schedules'!E36 -> 86828.535 | G12: ='Proj Schedules'!G36-'Proj Schedules'!F36 -> 85199.901
A13: Change in accrued expenses | C13: ='Proj Schedules'!C37-'Proj Schedules'!B37 -> 192048.27 | D13: ='Proj Schedules'!D37-'Proj Schedules'!C37 -> 204613.75 | E13: ='Proj Schedules'!E37-'Proj Schedules'!D37 -> 218058.33 | F13: ='Proj Schedules'!F37-'Proj Schedules'!E37 -> 232439.95 | G13: ='Proj Schedules'!G37-'Proj Schedules'!F37 -> 247824.3
A14: Change in deferred revenue | C14: ='Proj Schedules'!C38-'Proj Schedules'!B38 -> 132658.16 | D14: ='Proj Schedules'!D38-'Proj Schedules'!C38 -> 143608.47 | E14: ='Proj Schedules'!E38-'Proj Schedules'!D38 -> 99382.262 | F14: ='Proj Schedules'!F38-'Proj Schedules'!E38 -> 164287.16 | G14: ='Proj Schedules'!G38-'Proj Schedules'!F38 -> 113023.02
A15: Change in other non-current assets | C15: =-('Proj Schedules'!C41-'Proj Schedules'!B41) -> -582239.76 | D15: =-('Proj Schedules'!D41-'Proj Schedules'!C41) -> -630326.49 | E15: =-('Proj Schedules'!E41-'Proj Schedules'!D41) -> -682751.53 | F15: =-('Proj Schedules'!F41-'Proj Schedules'!E41) -> -739916.31 | G15: =-('Proj Schedules'!G41-'Proj Schedules'!F41) -> -802277.83
A16: Change in other non-current liabilities | C16: ='Proj Schedules'!C42-'Proj Schedules'!B42 -> 223437.99 | D16: ='Proj Schedules'!D42-'Proj Schedules'!C42 -> 239341.36 | E16: ='Proj Schedules'!E42-'Proj Schedules'!D42 -> 259247.68 | F16: ='Proj Schedules'!F42-'Proj Schedules'!E42 -> 280953.73 | G16: ='Proj Schedules'!G42-'Proj Schedules'!F42 -> 304633.03
A17: Net cash from operating activities | C17: =SUM(C5:C16) -> 10583808 | D17: =SUM(D5:D16) -> 11373790 | E17: =SUM(E5:E16) -> 12367772 | F17: =SUM(F5:F16) -> 13698099 | G17: =SUM(G5:G16) -> 15056605
A19: Cash flows from investing activities
A20: Capital expenditure | C20: =-'Proj Schedules'!C20 -> -728373.89 | D20: =-'Proj Schedules'!D20 -> -783184.89 | E20: =-'Proj Schedules'!E20 -> -842554.59 | F20: =-'Proj Schedules'!F20 -> -906895.14 | G20: =-'Proj Schedules'!G20 -> -976658.43
A21: Change in short-term investments | C21: =-('Proj Schedules'!C43-'Proj Schedules'!B43) -> 0 | D21: =-('Proj Schedules'!D43-'Proj Schedules'!C43) -> 0 | E21: =-('Proj Schedules'!E43-'Proj Schedules'!D43) -> 0 | F21: =-('Proj Schedules'!F43-'Proj Schedules'!E43) -> 0 | G21: =-('Proj Schedules'!G43-'Proj Schedules'!F43) -> 0
A22: Net cash from investing activities | C22: =SUM(C20:C21) -> -728373.89 | D22: =SUM(D20:D21) -> -783184.89 | E22: =SUM(E20:E21) -> -842554.59 | F22: =SUM(F20:F21) -> -906895.14 | G22: =SUM(G20:G21) -> -976658.43
A24: Cash flows from financing activities
A25: Repayment of debt | C25: =-'Proj Schedules'!C26 -> -1000000 | D25: =-'Proj Schedules'!D26 -> -1526000 | E25: =-'Proj Schedules'!E26 -> -3500000 | F25: =-'Proj Schedules'!F26 -> -4401000 | G25: =-'Proj Schedules'!G26 -> -2292000
A26: Proceeds from issuance of common stock | C26: ='Proj Schedules'!C47 -> 718662.24 | D26: ='Proj Schedules'!D47 -> 772742.43 | E26: ='Proj Schedules'!E47 -> 831320.53 | F26: ='Proj Schedules'!F47 -> 894803.2 | G26: ='Proj Schedules'!G47 -> 963636.32
A27: Share repurchases | C27: =-'Proj Schedules'!C48 -> -9127167 | D27: =-'Proj Schedules'!D48 -> -9127167 | E27: =-'Proj Schedules'!E48 -> -9127167 | F27: =-'Proj Schedules'!F48 -> -9127167 | G27: =-'Proj Schedules'!G48 -> -9127167
A28: Net cash from financing activities | C28: =SUM(C25:C27) -> -9408504.8 | D28: =SUM(D25:D27) -> -9880424.6 | E28: =SUM(E25:E27) -> -11795846 | F28: =SUM(F25:F27) -> -12633364 | G28: =SUM(G25:G27) -> -10455531
A30: Net change in cash | C30: =C17+C22+C28 -> 446928.92 | D30: =D17+D22+D28 -> 710180.39 | E30: =E17+E22+E28 -> -270628.81 | F30: =F17+F22+F28 -> 157840.17 | G30: =G17+G22+G28 -> 3624416.2
A31: Cash at beginning of year | C31: ='Balance Sheet Input'!$D$6 -> 9033681 | D31: =C32 -> 9480609.9 | E31: =D32 -> 10190790 | F31: =E32 -> 9920161.5 | G31: =F32 -> 10078002
A32: Cash at end of year | C32: =C31+C30 -> 9480609.9 | D32: =D31+D30 -> 10190790 | E32: =E31+E30 -> 9920161.5 | F32: =F31+F30 -> 10078002 | G32: =G31+G30 -> 13702418

Sheet Checks
A1: Netflix, Inc. — Model Integrity Checks
A2: All checks should read TRUE / 0 across every scenario. Re-verify after changing the scenario switch on the Model Control tab.
A4: CHECK 1 — Balance Sheet Balances (Assets = Liabilities + Equity)
A5: Year | C5: 2026E | D5: 2027E | E5: 2028E | F5: 2029E | G5: 2030E
A6: Assets - (Liabilities + Equity), $000s | C6: ='Projected BS'!C33 -> 0 | D6: ='Projected BS'!D33 -> 0 | E6: ='Projected BS'!E33 -> 0 | F6: ='Projected BS'!F33 -> 0 | G6: ='Projected BS'!G33 -> 0
A7: PASS? | C7: =IF(ROUND(C6,0)=0,"PASS","FAIL") -> PASS | D7: =IF(ROUND(D6,0)=0,"PASS","FAIL") -> PASS | E7: =IF(ROUND(E6,0)=0,"PASS","FAIL") -> PASS | F7: =IF(ROUND(F6,0)=0,"PASS","FAIL") -> PASS | G7: =IF(ROUND(G6,0)=0,"PASS","FAIL") -> PASS
A9: CHECK 2 — Cash Flow Statement Ties to Balance Sheet Cash
A10: Year | C10: 2026E | D10: 2027E | E10: 2028E | F10: 2029E | G10: 2030E
A11: CFS ending cash - BS cash, $000s | C11: ='Projected CFS'!C32-'Projected BS'!C5 -> 0 | D11: ='Projected CFS'!D32-'Projected BS'!D5 -> 0 | E11: ='Projected CFS'!E32-'Projected BS'!E5 -> 0 | F11: ='Projected CFS'!F32-'Projected BS'!F5 -> 0 | G11: ='Projected CFS'!G32-'Projected BS'!G5 -> 0
A12: PASS? | C12: =IF(ROUND(C11,0)=0,"PASS","FAIL") -> PASS | D12: =IF(ROUND(D11,0)=0,"PASS","FAIL") -> PASS | E12: =IF(ROUND(E11,0)=0,"PASS","FAIL") -> PASS | F12: =IF(ROUND(F11,0)=0,"PASS","FAIL") -> PASS | G12: =IF(ROUND(G11,0)=0,"PASS","FAIL") -> PASS
A14: CHECK 3 — Retained Earnings Rolls Forward with Net Income
A15: Year | C15: 2026E | D15: 2027E | E15: 2028E | F15: 2029E | G15: 2030E
A16: RE(t) - [RE(t-1) + Net Income(t)], $000s | C16: ='Projected BS'!C29-('Projected BS'!B29+'Projected PnL'!C13) -> 0 | D16: ='Projected BS'!D29-('Projected BS'!C29+'Projected PnL'!D13) -> 0 | E16: ='Projected BS'!E29-('Projected BS'!D29+'Projected PnL'!E13) -> 0 | F16: ='Projected BS'!F29-('Projected BS'!E29+'Projected PnL'!F13) -> 0 | G16: ='Projected BS'!G29-('Projected BS'!F29+'Projected PnL'!G13) -> 0
A17: PASS? | C17: =IF(ROUND(C16,0)=0,"PASS","FAIL") -> PASS | D17: =IF(ROUND(D16,0)=0,"PASS","FAIL") -> PASS | E17: =IF(ROUND(E16,0)=0,"PASS","FAIL") -> PASS | F17: =IF(ROUND(F16,0)=0,"PASS","FAIL") -> PASS | G17: =IF(ROUND(G16,0)=0,"PASS","FAIL") -> PASS
A19: CHECK 4 — Revenue Build Ties to Projected P&L
A20: Year | C20: 2026E | D20: 2027E | E20: 2028E | F20: 2029E | G20: 2030E
A21: Proj Schedules revenue - Projected PnL revenue, $000s | C21: ='Proj Schedules'!C9-'Projected PnL'!C4 -> 0 | D21: ='Proj Schedules'!D9-'Projected PnL'!D4 -> 0 | E21: ='Proj Schedules'!E9-'Projected PnL'!E4 -> 0 | F21: ='Proj Schedules'!F9-'Projected PnL'!F4 -> 0 | G21: ='Proj Schedules'!G9-'Projected PnL'!G4 -> 0
A22: PASS? | C22: =IF(ROUND(C21,0)=0,"PASS","FAIL") -> PASS | D22: =IF(ROUND(D21,0)=0,"PASS","FAIL") -> PASS | E22: =IF(ROUND(E21,0)=0,"PASS","FAIL") -> PASS | F22: =IF(ROUND(F21,0)=0,"PASS","FAIL") -> PASS | G22: =IF(ROUND(G21,0)=0,"PASS","FAIL") -> PASS
A24: CHECK 5 — Assumptions Tab Resolves the Active Scenario Correctly
A25: Assumptions!D50 (Selected COGS%, 2026E) matches CHOOSE() of Model Control switch? | B25: =IF(ROUND(Assumptions!D50,6)=ROUND(CHOOSE(MATCH('Model Control'!$B$3,{"Worst","Neutral","Best"},0),Assumptions!D47,Assumptions!D48,Assumptions!D49),6),"PASS","FAIL") -> PASS
A28: SCENARIO COMPARISON — proof that Worst / Neutral / Best all cascade through the model
A29: Static snapshot, computed by toggling Model Control!B3 through all three scenarios and capturing the output. The live model uses ONE switch (Model Control!B3) -- change it there to see any tab update in real time; this table exists only so all three cases are visible on one page at once.
A31: Metric | C31: Worst | D31: Neutral | E31: Best
A32: Total Revenue, 2026E ($000s) | C32: 47348803 | D32: 48558259 | E32: 49767716
A33: Total Revenue, 2030E ($000s) | C33: 57263751 | D33: 65110562 | E33: 73843073
A34: Net Income, 2026E ($000s) | C34: 9847161.4 | D34: 10926626 | E34: 11794844
A35: Net Income, 2030E ($000s) | C35: 11022588 | D35: 16725767 | E35: 21608345
A36: Operating Margin, 2026E | C36: 0.261 | D36: 0.275 | E36: 0.285
A37: Operating Margin, 2030E | C37: 0.234 | D37: 0.299 | E37: 0.333
A38: WACC | C38: 0.1092945 | D38: 0.1092945 | E38: 0.1092945
A39: Enterprise Value ($000s) | C39: 3.1855425e+08 | D39: 3.6916858e+08 | E39: 4.1158693e+08
A40: Equity Value ($000s) | C40: 3.1315378e+08 | D40: 3.637681e+08 | E40: 4.0618645e+08
A41: Implied Value per Share | C41: 72.09108 | D41: 83.742997 | E41: 93.508117
A42: Implied upside / (downside) vs. $73.42 market price | C42: -0.018100245 | D42: 0.14060197 | E42: 0.27360552
A44: Currently active scenario (live, updates with Model Control!B3): | C44: ='Model Control'!$C$4 -> Neutral Case
A47: DATA INTEGRITY AUDIT LOG (most recent full pass)
A49: Assumptions 2025A anchors (COGS, S&M, Tech&Dev, G&A, Other Current Assets, Accrued Exp, Deferred Rev, Tax Rate)
A50: Found: Were hardcoded and did not match the actual computed 2025A ratios from the historicals -- COGS was off by 2.5 percentage points (54.0% stated vs. 51.5% actual). These never corrupted the output statements (which always pulled 2025A directly from the historicals), but they undermined the Assumptions tab's own credibility and the projected trajectory's starting point.
A51: Resolution: FIXED -- 2025A cells are now live formulas pulling directly from the historicals (cannot drift again); 2026E-2030E trajectories were shifted by the same delta to preserve the analytical judgment about the pace of change while correcting the starting point.
A53: Model Control -- Depreciation as % of opening PP&E
A54: Found: Hardcoded at 7.0%. The actual 2025A ratio (D&A of property/equipment / opening PP&E) is 20.9% -- roughly 3x higher. This was understating projected depreciation, overstating net PP&E, and understating the D&A add-back in cash flow.
A55: Resolution: FIXED -- now a live formula linked to the historicals.
A57: Model Control -- Debt weighted-average interest rate
A58: Found: Hardcoded at a flat 5.0%, used to project forward interest expense -- but the model's own Debt tab computes an actual weighted-average effective rate of 4.76% from the real note-by-note maturity schedule. The two numbers disagreed for no reason.
A59: Resolution: FIXED -- now linked directly to Debt!D55, so there is exactly one interest rate in the model, not two.
A61: Proj Schedules!B31 -- 'Average debt' (2025A)
A62: Found: Formula mistakenly referenced 'CFS Input'!D45 (Interest Paid, $718.6mm) instead of computing an average debt balance. Harmless to output (2025A interest expense pulled from the actual historical figure directly, not from this cell), but wrong and misleading on inspection.
... A76: - Diluted share count in the DCF is static and does not shrink over time from ongoing buybacks, which would modestly increase per-share value in later years if modeled dynamically.

Sheet Chart Data
A1: Netflix, Inc. — Chart Data (all 3 scenarios computed in parallel, live-linked)
A2: Every cell here is a formula -- Worst/Neutral/Best are each computed directly from the Worst/Neutral/Best columns on the Assumptions tabs (not from the single Model Control switch), so all three scenarios are visible and update simultaneously. Historicals (2023A-2025A) are identical across scenarios (actuals).
A4: WORST CASE
A5: Year | B5: 2023A | C5: 2024A | D5: 2025A | E5: 2026E | F5: 2027E | G5: 2028E | H5: 2029E | I5: 2030E
A6: Total Revenue | B6: ='P&L Input'!C3 -> 33723297 | C6: ='P&L Input'!D3 -> 39000966 | D6: ='P&L Input'!E3 -> 45183036 | E6: =SUM(E7:E10) -> 47348803 | F6: =SUM(F7:F10) -> 49632441 | G6: =SUM(G7:G10) -> 52041036 | H6: =SUM(H7:H10) -> 54582130 | I6: =SUM(I7:I10) -> 57263751
A7: UCAN | D7: ='Revenue Modelling'!D4 -> 19957152 | E7: =D7*(1+Assumptions!D7) -> 20555867 | F7: =E7*(1+Assumptions!D7) -> 21172543 | G7: =F7*(1+Assumptions!D7) -> 21807719 | H7: =G7*(1+Assumptions!D7) -> 22461950 | I7: =H7*(1+Assumptions!D7) -> 23135809
A8: EMEA | D8: ='Revenue Modelling'!D6 -> 14514646 | E8: =D8*(1+Assumptions!D15) -> 15385525 | F8: =E8*(1+Assumptions!D15) -> 16308656 | G8: =F8*(1+Assumptions!D15) -> 17287176 | H8: =G8*(1+Assumptions!D15) -> 18324406 | I8: =H8*(1+Assumptions!D15) -> 19423871
A9: LATAM | D9: ='Revenue Modelling'!D8 -> 5357521 | E9: =D9*(1+Assumptions!D23) -> 5625397 | F9: =E9*(1+Assumptions!D23) -> 5906666.9 | G9: =F9*(1+Assumptions!D23) -> 6202000.2 | H9: =G9*(1+Assumptions!D23) -> 6512100.3 | I9: =H9*(1+Assumptions!D23) -> 6837705.3
A10: APAC | D10: ='Revenue Modelling'!D10 -> 5353717 | E10: =D10*(1+Assumptions!D31) -> 5782014.4 | F10: =E10*(1+Assumptions!D31) -> 6244575.5 | G10: =F10*(1+Assumptions!D31) -> 6744141.5 | H10: =G10*(1+Assumptions!D31) -> 7283672.9 | I10: =H10*(1+Assumptions!D31) -> 7866366.7
A12: Cost of Revenue | B12: ='P&L Input'!C4 -> 19715368 | C12: ='P&L Input'!D4 -> 21038464 | D12: ='P&L Input'!E4 -> 23275329 | E12: =E6*Assumptions!D47 -> 24485676 | F12: =F6*Assumptions!E47 -> 25765888 | G12: =G6*Assumptions!F47 -> 27068312 | H12: =H6*Assumptions!G47 -> 28499186 | I12: =I6*Assumptions!H47 -> 30071143
A13: Gross Profit | B13: =B6-B12 -> 14007929 | C13: =C6-C12 -> 17962502 | D13: =D6-D12 -> 21907707 | E13: =E6-E12 -> 22863127 | F13: =F6-F12 -> 23866553 | G13: =G6-G12 -> 24972724 | H13: =H6-H12 -> 26082944 | I13: =I6-I12 -> 27192609
A14: Sales & Marketing | B14: ='P&L Input'!C6 -> 2657883 | C14: ='P&L Input'!D6 -> 2917554 | D14: ='P&L Input'!E6 -> 3301306 | E14: =E6*Assumptions!D55 -> 3601586.7 | F14: =F6*Assumptions!E55 -> 3874556.5 | G14: =G6*Assumptions!F55 -> 4166665.6 | H14: =H6*Assumptions!G55 -> 4479282.5 | I14: =I6*Assumptions!H55 -> 4756613.5
A15: Technology & Development | B15: ='P&L Input'!C7 -> 2675758 | C15: ='P&L Input'!D7 -> 2925295 | D15: ='P&L Input'!E7 -> 3391390 | E15: =E6*Assumptions!D63 -> 3648651.4 | F15: =F6*Assumptions!E63 -> 3874258.7 | G15: =G6*Assumptions!F63 -> 4166353.3 | H15: =H6*Assumptions!G63 -> 4424372.9 | I15: =I6*Assumptions!H63 -> 4756269.9
A16: General & Administrative | B16: ='P&L Input'!C8 -> 1720285 | C16: ='P&L Input'!D8 -> 1702039 | D16: ='P&L Input'!E8 -> 1888408 | E16: =E6*Assumptions!D71 -> 2073640.8 | F16: =F6*Assumptions!E71 -> 2223285.2 | G16: =G6*Assumptions!F71 -> 2435260.3 | H16: =H6*Assumptions!G71 -> 2608752.9 | I16: =I6*Assumptions!H71 -> 2851448.5
A17: Total Operating Expenses (S&M+T&D+G&A) | B17: =B14+B15+B16 -> 7053926 | C17: =C14+C15+C16 -> 7544888 | D17: =D14+D15+D16 -> 8581104 | E17: =E14+E15+E16 -> 9323878.9 | F17: =F14+F15+F16 -> 9972100.5 | G17: =G14+G15+G16 -> 10768279 | H17: =H14+H15+H16 -> 11512408 | I17: =I14+I15+I16 -> 12364332
A18: Operating Income | B18: =B13-B17 -> 6954003 | C18: =C13-C17 -> 10417614 | D18: =D13-D17 -> 13326603 | E18: =E13-E17 -> 13539248 | F18: =F13-F17 -> 13894453 | G18: =G13-G17 -> 14204445 | H18: =H13-H17 -> 14570536 | I18: =I13-I17 -> 14828277
A19: Operating Margin % | B19: =B18/B6 -> 0.20620768 | C19: =C18/C6 -> 0.26711169 | D19: =D18/D6 -> 0.29494705 | E19: =E18/E6 -> 0.285947 | F19: =F18/F6 -> 0.279947 | G19: =G18/G6 -> 0.272947 | H19: =H18/H6 -> 0.266947 | I19: =I18/I6 -> 0.258947
A20: Interest Expense (contractual, same all scenarios) | B20: ='P&L Input'!C11 -> -699826 | C20: ='P&L Input'!D11 -> -718733 | D20: ='P&L Input'!E11 -> -776510 | E20: =-'Proj Schedules'!C32 -> -664630.99 | F20: =-'Proj Schedules'!D32 -> -604512.19 | G20: =-'Proj Schedules'!E32 -> -484893.39 | H20: =-'Proj Schedules'!F32 -> -296849.59 | I20: =-'Proj Schedules'!G32 -> -137556.19
A21: Interest & Other Income (Expense) | B21: ='P&L Input'!C12 -> -48772 | C21: ='P&L Input'!D12 -> 266776 | D21: ='P&L Input'!E12 -> 172459 | E21: =Assumptions!D111 -> -75000 | F21: =Assumptions!E111 -> -50000 | G21: =Assumptions!F111 -> -25000 | H21: =Assumptions!G111 -> 0 | I21: =Assumptions!H111 -> 25000
A22: EBT | B22: =B18+B20+B21 -> 6205405 | C22: =C18+C20+C21 -> 9965657 | D22: =D18+D20+D21 -> 12722552 | E22: =E18+E20+E21 -> 12799617 | F22: =F18+F20+F21 -> 13239941 | G22: =G18+G20+G21 -> 13694551 | H22: =H18+H20+H21 -> 14273686 | I22: =I18+I20+I21 -> 14715720
A23: Provision for Income Taxes | B23: ='P&L Input'!C14 -> -797415 | C23: ='P&L Input'!D14 -> -1254026 | D23: ='P&L Input'!E14 -> -1741351 | E23: =-E22*Assumptions!D119 -> -1879892.6 | F23: =-F22*Assumptions!E119 -> -2010763.1 | G23: =-G22*Assumptions!F119 -> -2148278 | H23: =-H22*Assumptions!G119 -> -2310495.9 | I23: =-I22*Assumptions!H119 -> -2455627
A24: Net Income | B24: =B22+B23 -> 5407990 | C24: =C22+C23 -> 8711631 | D24: =D22+D23 -> 10981201 | E24: =E22+E23 -> 10919725 | F24: =F22+F23 -> 11229178 | G24: =G22+G23 -> 11546273 | H24: =H22+H23 -> 11963190 | I24: =I22+I23 -> 12260093
A25: Net Margin % | B25: =B24/B6 -> 0.16036362 | C25: =C24/C6 -> 0.22336962 | D25: =D24/D6 -> 0.24303814 | E25: =E24/E6 -> 0.23062303 | F25: =F24/F6 -> 0.22624673 | G25: =G24/G6 -> 0.22186863 | H25: =H24/H6 -> 0.21917779 | I25: =I24/I6 -> 0.21409868
A26: Free Cash Flow (CFO - Capex), historicals only | B26: ='CFS Input'!B20+'CFS Input'!B23 -> 6925749 | C26: ='CFS Input'!C20+'CFS Input'!C23 -> 6921826 | D26: ='CFS Input'!D20+'CFS Input'!D23 -> 9461053
A29: NEUTRAL CASE
A30: Year | B30: 2023A | C30: 2024A | D30: 2025A | E30: 2026E | F30: 2027E | G30: 2028E | H30: 2029E | I30: 2030E
A31: Total Revenue | B31: ='P&L Input'!C3 -> 33723297 | C31: ='P&L Input'!D3 -> 39000966 | D31: ='P&L Input'!E3 -> 45183036 | E31: =SUM(E32:E35) -> 48558259 | F31: =SUM(F32:F35) -> 52212326 | G31: =SUM(G32:G35) -> 56170306 | H31: =SUM(H32:H35) -> 60459676 | I31: =SUM(I32:I35) -> 65110562
A32: UCAN | D32: ='Revenue Modelling'!D4 -> 19957152 | E32: =D32*(1+Assumptions!D8) -> 20955010 | F32: =E32*(1+Assumptions!D8) -> 22002760 | G32: =F32*(1+Assumptions!D8) -> 23102898 | H32: =G32*(1+Assumptions!D8) -> 24258043 | I32: =H32*(1+Assumptions!D8) -> 25470945
A33: EMEA | D33: ='Revenue Modelling'!D6 -> 14514646 | E33: =D33*(1+Assumptions!D16) -> 15820964 | F33: =E33*(1+Assumptions!D16) -> 17244851 | G33: =F33*(1+Assumptions!D16) -> 18796887 | H33: =G33*(1+Assumptions!D16) -> 20488607 | I33: =H33*(1+Assumptions!D16) -> 22332582
A34: LATAM | D34: ='Revenue Modelling'!D8 -> 5357521 | E34: =D34*(1+Assumptions!D24) -> 5786122.7 | F34: =E34*(1+Assumptions!D24) -> 6249012.5 | G34: =F34*(1+Assumptions!D24) -> 6748933.5 | H34: =G34*(1+Assumptions!D24) -> 7288848.2 | I34: =H34*(1+Assumptions!D24) -> 7871956
A35: APAC | D35: ='Revenue Modelling'!D10 -> 5353717 | E35: =D35*(1+Assumptions!D32) -> 5996163 | F35: =E35*(1+Assumptions!D32) -> 6715702.6 | G35: =F35*(1+Assumptions!D32) -> 7521586.9 | H35: =G35*(1+Assumptions!D32) -> 8424177.3 | I35: =H35*(1+Assumptions!D32) -> 9435078.6
A37: Cost of Revenue | B37: ='P&L Input'!C4 -> 19715368 | C37: ='P&L Input'!D4 -> 21038464 | D37: ='P&L Input'!E4 -> 23275329 | E37: =E31*Assumptions!D48 -> 24868336 | F37: =F31*Assumptions!E48 -> 26583070 | G37: =G31*Assumptions!F48 -> 28429702 | H37: =H31*Assumptions!G48 -> 30419319 | I37: =I31*Assumptions!H48 -> 32564006
A38: Gross Profit | B38: =B31-B37 -> 14007929 | C38: =C31-C37 -> 17962502 | D38: =D31-D37 -> 21907707 | E38: =E31-E37 -> 23689924 | F38: =F31-F37 -> 25629256 | G38: =G31-G37 -> 27740604 | H38: =H31-H37 -> 30040357 | I38: =I31-I37 -> 32546556
A39: Sales & Marketing | B39: ='P&L Input'!C6 -> 2657883 | C39: ='P&L Input'!D6 -> 2917554 | D39: ='P&L Input'!E6 -> 3301306 | E39: =E31*Assumptions!D56 -> 3499351 | F39: =F31*Assumptions!E56 -> 3710469 | G39: =G31*Assumptions!F56 -> 3935572.5 | H39: =H31*Assumptions!G56 -> 4175647.5 | I39: =I31*Assumptions!H56 -> 4431750.4
A40: Technology & Development | B40: ='P&L Input'!C7 -> 2675758 | C40: ='P&L Input'!D7 -> 2925295 | D40: ='P&L Input'!E7 -> 3391390 | E40: =E31*Assumptions!D64 -> 3644734.4 | F40: =F31*Assumptions!E64 -> 3866792.7 | G40: =G31*Assumptions!F64 -> 4103746.4 | H40: =H31*Assumptions!G64 -> 4356663.8 | I40: =I31*Assumptions!H64 -> 4626691.4
A41: General & Administrative | B41: ='P&L Input'!C8 -> 1720285 | C41: ='P&L Input'!D8 -> 1702039 | D41: ='P&L Input'!E8 -> 1888408 | E41: =E31*Assumptions!D72 -> 1980934.2 | F41: =F31*Assumptions!E72 -> 2077789.5 | G41: =G31*Assumptions!F72 -> 2179127 | H41: =H31*Assumptions!G72 -> 2285073.4 | I41: =I31*Assumptions!H72 -> 2395743.1
A42: Total Operating Expenses (S&M+T&D+G&A) | B42: =B39+B40+B41 -> 7053926 | C42: =C39+C40+C41 -> 7544888 | D42: =D39+D40+D41 -> 8581104 | E42: =E39+E40+E41 -> 9125019.6 | F42: =F39+F40+F41 -> 9655051.1 | G42: =G39+G40+G41 -> 10218446 | H42: =H39+H40+H41 -> 10817385 | I42: =I39+I40+I41 -> 11454185
A43: Operating Income | B43: =B38-B42 -> 6954003 | C43: =C38-C42 -> 10417614 | D43: =D38-D42 -> 13326603 | E43: =E38-E42 -> 14564904 | F43: =F38-F42 -> 15974205 | G43: =G38-G42 -> 17522158 | H43: =H38-H42 -> 19222973 | I43: =I38-I42 -> 21092371
A44: Operating Margin % | B44: =B43/B31 -> 0.20620768 | C44: =C43/C31 -> 0.26711169 | D44: =D43/D31 -> 0.29494705 | E44: =E43/E31 -> 0.299947 | F44: =F43/F31 -> 0.305947 | G44: =G43/G31 -> 0.311947 | H44: =H43/H31 -> 0.317947 | I44: =I43/I31 -> 0.323947
A45: Interest Expense (contractual, same all scenarios) | B45: ='P&L Input'!C11 -> -699826 | C45: ='P&L Input'!D11 -> -718733 | D45: ='P&L Input'!E11 -> -776510 | E45: =-'Proj Schedules'!C32 -> -664630.99 | F45: =-'Proj Schedules'!D32 -> -604512.19 | G45: =-'Proj Schedules'!E32 -> -484893.39 | H45: =-'Proj Schedules'!F32 -> -296849.59 | I45: =-'Proj Schedules'!G32 -> -137556.19
A46: Interest & Other Income (Expense) | B46: ='P&L Input'!C12 -> -48772 | C46: ='P&L Input'!D12 -> 266776 | D46: ='P&L Input'!E12 -> 172459 | E46: =Assumptions!D112 -> 50000 | F46: =Assumptions!E112 -> 75000 | G46: =Assumptions!F112 -> 100000 | H46: =Assumptions!G112 -> 100000 | I46: =Assumptions!H112 -> 125000
A47: EBT | B47: =B43+B45+B46 -> 6205405 | C47: =C43+C45+C46 -> 9965657 | D47: =D43+D45+D46 -> 12722552 | E47: =E43+E45+E46 -> 13950273 | F47: =F43+F45+F46 -> 15444692 | G47: =G43+G45+G46 -> 17137265 | H47: =H43+H45+H46 -> 19026123 | I47: =I43+I45+I46 -> 21079815
A48: Provision for Income Taxes | B48: ='P&L Input'!C14 -> -797415 | C48: ='P&L Input'!D14 -> -1254026 | D48: ='P&L Input'!E14 -> -1741351 | E48: =-E47*Assumptions!D120 -> -1909387.9 | F48: =-F47*Assumptions!E120 -> -2113930.5 | G48: =-G47*Assumptions!F120 -> -2345594.6 | H48: =-H47*Assumptions!G120 -> -2604124.5 | I48: =-I47*Assumptions!H120 -> -2885215.4
A49: Net Income | B49: =B47+B48 -> 5407990 | C49: =C47+C48 -> 8711631 | D49: =D47+D48 -> 10981201 | E49: =E47+E48 -> 12040885 | F49: =F47+F48 -> 13330762 | G49: =G47+G48 -> 14791670 | H49: =H47+H48 -> 16421998 | I49: =I47+I48 -> 18194600
A50: Net Margin % | B50: =B49/B31 -> 0.16036362 | C50: =C49/C31 -> 0.22336962 | D50: =D49/D31 -> 0.24303814 | E50: =E49/E31 -> 0.24796781 | F50: =F49/F31 -> 0.25531829 | G50: =G49/G31 -> 0.26333612 | H50: =H49/H31 -> 0.27161903 | I50: =I49/I31 -> 0.2794416
A51: Free Cash Flow (CFO - Capex), historicals only | B51: ='CFS Input'!B20+'CFS Input'!B23 -> 6925749 | C51: ='CFS Input'!C20+'CFS Input'!C23 -> 6921826 | D51: ='CFS Input'!D20+'CFS Input'!D23 -> 9461053
A54: BEST CASE
A55: Year | B55: 2023A | C55: 2024A | D55: 2025A | E55: 2026E | F55: 2027E | G55: 2028E | H55: 2029E | I55: 2030E
A56: Total Revenue | B56: ='P&L Input'!C3 -> 33723297 | C56: ='P&L Input'!D3 -> 39000966 | D56: ='P&L Input'!E3 -> 45183036 | E56: =SUM(E57:E60) -> 49767716 | F56: =SUM(F57:F60) -> 54861078 | G56: =SUM(G57:G60) -> 60524109 | H56: =SUM(H57:H60) -> 66825577 | I56: =SUM(I57:I60) -> 73843073
A57: UCAN | D57: ='Revenue Modelling'!D4 -> 19957152 | E57: =D57*(1+Assumptions!D9) -> 21354153 | F57: =E57*(1+Assumptions!D9) -> 22848943 | G57: =F57*(1+Assumptions!D9) -> 24448369 | H57: =G57*(1+Assumptions!D9) -> 26159755 | I57: =H57*(1+Assumptions!D9) -> 27990938
A58: EMEA | D58: ='Revenue Modelling'!D6 -> 14514646 | E58: =D58*(1+Assumptions!D17) -> 16256404 | F58: =E58*(1+Assumptions!D17) -> 18207172 | G58: =F58*(1+Assumptions!D17) -> 20392033 | H58: =G58*(1+Assumptions!D17) -> 22839076 | I58: =H58*(1+Assumptions!D17) -> 25579766
A59: LATAM | D59: ='Revenue Modelling'!D8 -> 5357521 | E59: =D59*(1+Assumptions!D25) -> 5946848.3 | F59: =E59*(1+Assumptions!D25) -> 6601001.6 | G59: =F59*(1+Assumptions!D25) -> 7327111.8 | H59: =G59*(1+Assumptions!D25) -> 8133094.1 | I59: =H59*(1+Assumptions!D25) -> 9027734.5
A60: APAC | D60: ='Revenue Modelling'!D10 -> 5353717 | E60: =D60*(1+Assumptions!D33) -> 6210311.7 | F60: =E60*(1+Assumptions!D33) -> 7203961.6 | G60: =F60*(1+Assumptions!D33) -> 8356595.5 | H60: =G60*(1+Assumptions!D33) -> 9693650.7 | I60: =H60*(1+Assumptions!D33) -> 11244635
A62: Cost of Revenue | B62: ='P&L Input'!C4 -> 19715368 | C62: ='P&L Input'!D4 -> 21038464 | D62: ='P&L Input'!E4 -> 23275329 | E62: =E56*Assumptions!D49 -> 25288669 | F62: =F56*Assumptions!E49 -> 27492752 | G62: =G56*Assumptions!F49 -> 29907020 | H62: =H56*Assumptions!G49 -> 32619836 | I62: =I56*Assumptions!H49 -> 35676099
A63: Gross Profit | B63: =B56-B62 -> 14007929 | C63: =C56-C62 -> 17962502 | D63: =D56-D62 -> 21907707 | E63: =E56-E62 -> 24479047 | F63: =F56-F62 -> 27368327 | G63: =G56-G62 -> 30617089 | H63: =H56-H62 -> 34205741 | I63: =I56-I62 -> 38166974
A64: Sales & Marketing | B64: ='P&L Input'!C6 -> 2657883 | C64: ='P&L Input'!D6 -> 2917554 | D64: ='P&L Input'!E6 -> 3301306 | E64: =E56*Assumptions!D57 -> 3486975 | F64: =F56*Assumptions!E57 -> 3679258.2 | G64: =G56*Assumptions!F57 -> 3877477.1 | H64: =H56*Assumptions!G57 -> 4147529.4 | I64: =I56*Assumptions!H57 -> 4435384.2
A65: Technology & Development | B65: ='P&L Input'!C7 -> 2675758 | C65: ='P&L Input'!D7 -> 2925295 | D65: ='P&L Input'!E7 -> 3391390 | E65: =E56*Assumptions!D65 -> 3635979.6 | F65: =F56*Assumptions!E65 -> 3898373.4 | G65: =G56*Assumptions!F65 -> 4240258.6 | H65: =H56*Assumptions!G65 -> 4548081.9 | I65: =I56*Assumptions!H65 -> 4951842.6
A66: General & Administrative | B66: ='P&L Input'!C8 -> 1720285 | C66: ='P&L Input'!D8 -> 1702039 | D66: ='P&L Input'!E8 -> 1888408 | E66: =E56*Assumptions!D73 -> 1930738.5 | F66: =F56*Assumptions!E73 -> 2018613.4 | G66: =G56*Assumptions!F73 -> 2105936.4 | H66: =H56*Assumptions!G73 -> 2258370.4 | I66: =I56*Assumptions!H73 -> 2347840.5
A67: Total Operating Expenses (S&M+T&D+G&A) | B67: =B64+B65+B66 -> 7053926 | C67: =C64+C65+C66 -> 7544888 | D67: =D64+D65+D66 -> 8581104 | E67: =E64+E65+E66 -> 9053693.2 | F67: =F64+F65+F66 -> 9596245 | G67: =G64+G65+G66 -> 10223672 | H67: =H64+H65+H66 -> 10953982 | I67: =I64+I65+I66 -> 11735067
A68: Operating Income | B68: =B63-B67 -> 6954003 | C68: =C63-C67 -> 10417614 | D68: =D63-D67 -> 13326603 | E68: =E63-E67 -> 15425354 | F68: =F63-F67 -> 17772082 | G68: =G63-G67 -> 20393417 | H68: =H63-H67 -> 23251759 | I68: =I63-I67 -> 26431906
A69: Operating Margin % | B69: =B68/B56 -> 0.20620768 | C69: =C68/C56 -> 0.26711169 | D69: =D68/D56 -> 0.29494705 | E69: =E68/E56 -> 0.309947 | F69: =F68/F56 -> 0.323947 | G69: =G68/G56 -> 0.336947 | H69: =H68/H56 -> 0.347947 | I69: =I68/I56 -> 0.357947
A70: Interest Expense (contractual, same all scenarios) | B70: ='P&L Input'!C11 -> -699826 | C70: ='P&L Input'!D11 -> -718733 | D70: ='P&L Input'!E11 -> -776510 | E70: =-'Proj Schedules'!C32 -> -664630.99 | F70: =-'Proj Schedules'!D32 -> -604512.19 | G70: =-'Proj Schedules'!E32 -> -484893.39 | H70: =-'Proj Schedules'!F32 -> -296849.59 | I70: =-'Proj Schedules'!G32 -> -137556.19
A71: Interest & Other Income (Expense) | B71: ='P&L Input'!C12 -> -48772 | C71: ='P&L Input'!D12 -> 266776 | D71: ='P&L Input'!E12 -> 172459 | E71: =Assumptions!D113 -> 150000 | F71: =Assumptions!E113 -> 175000 | G71: =Assumptions!F113 -> 200000 | H71: =Assumptions!G113 -> 225000 | I71: =Assumptions!H113 -> 250000
A72: EBT | B72: =B68+B70+B71 -> 6205405 | C72: =C68+C70+C71 -> 9965657 | D72: =D68+D70+D71 -> 12722552 | E72: =E68+E70+E71 -> 14910723 | F72: =F68+F70+F71 -> 17342570 | G72: =G68+G70+G71 -> 20108524 | H72: =H68+H70+H71 -> 23179909 | I72: =I68+I70+I71 -> 26544350
A73: Provision for Income Taxes | B73: ='P&L Input'!C14 -> -797415 | C73: ='P&L Input'!D14 -> -1254026 | D73: ='P&L Input'!E14 -> -1741351 | E73: =-E72*Assumptions!D121 -> -1966292 | F73: =-F72*Assumptions!E121 -> -2252296.9 | G73: =-G72*Assumptions!F121 -> -2551188.5 | H73: =-H72*Assumptions!G121 -> -2894498.5 | I73: =-I72*Assumptions!H121 -> -3234986.5
A74: Net Income | B74: =B72+B73 -> 5407990 | C74: =C72+C73 -> 8711631 | D74: =D72+D73 -> 10981201 | E74: =E72+E73 -> 12944431 | F74: =F72+F73 -> 15090273 | G74: =G72+G73 -> 17557335 | H74: =H72+H73 -> 20285411 | I74: =I72+I73 -> 23309364
A75: Net Margin % | B75: =B74/B56 -> 0.16036362 | C75: =C74/C56 -> 0.22336962 | D75: =D74/D56 -> 0.24303814 | E75: =E74/E56 -> 0.26009695 | F75: =F74/F56 -> 0.27506336 | G75: =G74/G56 -> 0.29008829 | H75: =H74/H56 -> 0.30355759 | I75: =I74/I56 -> 0.3156608
A76: Free Cash Flow (CFO - Capex), historicals only | B76: ='CFS Input'!B20+'CFS Input'!B23 -> 6925749 | C76: ='CFS Input'!C20+'CFS Input'!C23 -> 6921826 | D76: ='CFS Input'!D20+'CFS Input'!D23 -> 9461053

Sheet Charts
A1: Netflix, Inc. — Scenario Charts (Worst / Neutral / Best)
A2: Source data: Chart Data tab. All three scenarios computed and plotted simultaneously; historicals (2023A-2025A) are actuals shared by all three lines.

Sheet WACC
A1: Netflix, Inc. — Weighted Average Cost of Capital (WACC)
A2: (USD in thousands unless noted; market data as of July 2026)
A4: Cost of Equity (CAPM)
A5: Risk-free rate (10-yr U.S. Treasury) | B5: 0.045 | C5: Source: U.S. Treasury / FRED DGS10, ~4.5-4.6% as of July 2026.
A6: Equity risk premium | B6: 0.055 | C6: Source: long-run U.S. market ERP estimate (Damodaran-style), ~5.0-5.5%.
A7: Levered beta | B7: 1.23 | C7: Source: GuruFocus 3-yr beta, ~1.2. Reflects NFLX volatility vs. legacy media/streaming peers; other providers show a wider 1.2-1.7 range depending on lookback window.
A8: Cost of equity = Rf + Beta x ERP | B8: =B5+B7*B6 -> 0.11265
A10: Cost of Debt
A11: Pre-tax cost of debt (weighted-avg effective rate) | B11: =Debt!D55 -> 0.0476 | C11: Source: FY2025 10-K Note 7, weighted-average effective interest rate on senior notes.
A12: Marginal tax rate | B12: 0.21 | C12: U.S. federal statutory rate, used for the debt tax shield (distinct from the effective book tax rate in Assumptions).
A13: After-tax cost of debt | B13: =B11*(1-B12) -> 0.037604
A15: Capital Structure (Market Values)
A16: Market value of equity | B16: 309000000 | C16: Market cap ~$309bn (NFLX @ ~$73.42/sh x ~4.21bn shares o/s, per Morningstar, July 10, 2026), converted to $000s.
A17: Market value of debt (book value used as proxy) | B17: ='Balance Sheet Input'!D21+'Balance Sheet Input'!D24 -> 14462836 | C17: FY2025 10-K balance sheet: short-term debt + long-term debt.
A18: Total capital | B18: =B16+B17 -> 323462836
A19: Weight of equity | B19: =B16/B18 -> 0.95528749
A20: Weight of debt | B20: =B17/B18 -> 0.044712512
A22: WACC = We x Ke + Wd x Kd(after-tax) | B22: =B19*B8+B20*B13 -> 0.1092945

Sheet DCF
A1: Netflix, Inc. — Discounted Cash Flow Valuation
A2: =CONCATENATE("Scenario: ",'Model Control'!$C$4," | WACC: ",TEXT(WACC!$B$22,"0.00%")) -> Scenario: Neutral Case | WACC: 10.93%
A3: (USD in thousands, except per-share)
B4: Formula | C4: 2026E | D4: 2027E | E4: 2028E | F4: 2029E | G4: 2030E
A5: EBIT (Operating income) | C5: ='Projected PnL'!C10 -> 14564904 | D5: ='Projected PnL'!D10 -> 15974205 | E5: ='Projected PnL'!E10 -> 17522158 | F5: ='Projected PnL'!F10 -> 19222973 | G5: ='Projected PnL'!G10 -> 21092371
A6: Less: unlevered cash taxes (EBIT x tax rate) | C6: =-C5*'Proj Drivers'!C14 -> -1993513 | D6: =-D5*'Proj Drivers'!D14 -> -2186405.3 | E6: =-E5*'Proj Drivers'!E14 -> -2398275.3 | F6: =-F5*'Proj Drivers'!F14 -> -2631067.5 | G6: =-G5*'Proj Drivers'!G14 -> -2886933.9
A7: NOPAT | C7: =C5+C6 -> 12571391 | D7: =D5+D6 -> 13787799 | E7: =E5+E6 -> 15123883 | F7: =F5+F6 -> 16591905 | G7: =G5+G6 -> 18205437
A8: Add: D&A (PP&E depreciation + content amortization) | C8: ='Proj Schedules'!C21+'Proj Schedules'!C14 -> 16808475 | D8: ='Proj Schedules'!D21+'Proj Schedules'!D14 -> 18081674 | E8: ='Proj Schedules'!E21+'Proj Schedules'!E14 -> 19688857 | F8: ='Proj Schedules'!F21+'Proj Schedules'!F14 -> 21557417 | G8: ='Proj Schedules'!G21+'Proj Schedules'!G14 -> 23660944
A9: Less: Capex (PP&E) | C9: ='Projected CFS'!C20 -> -728373.89 | D9: ='Projected CFS'!D20 -> -783184.89 | E9: ='Projected CFS'!E20 -> -842554.59 | F9: ='Projected CFS'!F20 -> -906895.14 | G9: ='Projected CFS'!G20 -> -976658.43
A10: Less: Net content spend (additions less amortization) | C10: =-('Proj Schedules'!C13-'Proj Schedules'!C14) -> -2417082.7 | D10: =-('Proj Schedules'!D13-'Proj Schedules'!D14) -> -3089169.2 | E10: =-('Proj Schedules'!E13-'Proj Schedules'!E14) -> -3613275.3 | F10: =-('Proj Schedules'!F13-'Proj Schedules'!F14) -> -4082197.4 | G10: =-('Proj Schedules'!G13-'Proj Schedules'!G14) -> -4544214.4
A11: Less: (Increase) / add: decrease in other net working capital | C11: ='Projected CFS'!C11+'Projected CFS'!C12+'Projected CFS'!C13+'Projected CFS'!C14+'Projected CFS'!C15+'Projected CFS'!C16 -> -262904.18 | D11: ='Projected CFS'!D11+'Projected CFS'!D12+'Projected CFS'!D13+'Projected CFS'!D14+'Projected CFS'!D15+'Projected CFS'!D16 -> -236638.94 | E11: ='Projected CFS'!E11+'Projected CFS'!E12+'Projected CFS'!E13+'Projected CFS'!E14+'Projected CFS'!E15+'Projected CFS'!E16 -> -312501.75 | F11: ='Projected CFS'!F11+'Projected CFS'!F12+'Projected CFS'!F13+'Projected CFS'!F14+'Projected CFS'!F15+'Projected CFS'!F16 -> -282100.17 | G11: ='Projected CFS'!G11+'Projected CFS'!G12+'Projected CFS'!G13+'Projected CFS'!G14+'Projected CFS'!G15+'Projected CFS'!G16 -> -379933.36
A13: Unlevered Free Cash Flow (UFCF) | C13: =C7+C8+C9+C10+C11 -> 25971505 | D13: =D7+D8+D9+D10+D11 -> 27760480 | E13: =E7+E8+E9+E10+E11 -> 30044408 | F13: =F7+F8+F9+F10+F11 -> 32878130 | G13: =G7+G8+G9+G10+G11 -> 35965575
A15: Discount period (years) | C15: =1 -> 1 | D15: =2 -> 2 | E15: =3 -> 3 | F15: =4 -> 4 | G15: =5 -> 5
A16: Discount factor @ WACC | C16: =1/(1+WACC!$B$22)^C15 -> 0.90147386 | D16: =1/(1+WACC!$B$22)^D15 -> 0.81265512 | E16: =1/(1+WACC!$B$22)^E15 -> 0.73258735 | F16: =1/(1+WACC!$B$22)^F15 -> 0.66040835 | G16: =1/(1+WACC!$B$22)^G15 -> 0.59534086
A17: PV of UFCF | C17: =C13*C16 -> 23412633 | D17: =D13*D16 -> 22559696 | E17: =E13*E16 -> 22010153 | F17: =F13*F16 -> 21712991 | G17: =G13*G16 -> 21411777
A19: Sum of PV of UFCF (2026E-2030E) | C19: =SUM(C17:G17) -> 1.1110725e+08
A21: Terminal Value (Gordon Growth Method)
A22: Long-term perpetuity growth rate (g) | C22: 0.03
A23: -- assumption grounded in long-run nominal GDP/streaming-market maturity growth, held below WACC.
A24: Terminal UFCF = UFCF(2030E) x (1+g) | C24: =G13*(1+C22) -> 37044543
A25: Terminal Value = Terminal UFCF / (WACC - g) | C25: =C24/(WACC!$B$22-C22) -> 4.6717667e+08
A26: PV of Terminal Value | C26: =C25*G16 -> 2.7812936e+08
A28: Enterprise Value = Sum PV(UFCF) + PV(Terminal Value) | C28: =C19+C26 -> 3.8923661e+08
A29: memo: % of EV from terminal value | C29: =C26/C28 -> 0.71455087
A31: Less: Total Debt (2025A book value) | C31: =-('Balance Sheet Input'!D21+'Balance Sheet Input'!D24) -> -14462836
A32: Add: Cash & Short-Term Investments (2025A) | C32: ='Balance Sheet Input'!D6+'Balance Sheet Input'!D7 -> 9062359
A33: Equity Value | C33: =C28+C31+C32 -> 3.8383614e+08
A35: Diluted shares outstanding (000s) | C35: 4343863
A36: -- Source: FY2025 10-K weighted-average diluted shares.
A37: Implied Value per Share | C37: =C33/C35 -> 88.362855
A38: Current market price (for reference, July 2026) | C38: 73.42
A39: -- Source: Morningstar/Robinhood quote, July 10-11, 2026.
A40: Implied upside / (downside) vs. current price | C40: =C37/C38-1 -> 0.20352567
